Workbook

Sheet README
A1: 東アジア歴史認識コーパス — データブック
A2: 日本・韓国・中国政府の歴史認識関連公式発話 コーディングデータ(2026-09-23時点)
A4: このブックの構成
A5: README | B5: このシート。
A6: Summary_Stats | B6: 国別・発話者レベル別の集計(すべてMainAxis_101シートを参照する数式)。データを修正すると自動で再計算される。
A7: Sources_102 | B7: 主軸101件+歴史的画期1件、計102件それぞれについて、本文を取得した一次資料URL(および代替取得したアーカイブURL)を一覧化。
A8: MainAxis_101 | B8: 本編の主軸コーパス。2020-2026年、日本41件(首脳HEAD 37+外務大臣級MINISTER 4)・韓国30件・中国30件、計101件。全件、原文を読んだうえで手動コーディング済み(classification_confidence=HIGH/MEDIUM)。
A9: LandmarkAnchor_1 | B9: 歴史的画期(landmark anchor)として別枠で扱う1995年村山談話。主軸とは異なる目的的サンプリング(時系列分析用ではなく参照点)。
A10: BacklogReview_718 | B10: 日本側の未採用候補718件の全数レビュー結果。full_review_status列がPROMOTED(7件、MainAxis_101に採用済み)/EXCLUDED(711件、理由をfull_review_reason列に記録)。
A12: 元データファイル(リポジトリ toruoga/toruoga)
A13: pilot_east_asia_2020_2025.csv | B13: MainAxis_101 シートの元CSV。
A14: landmark_anchors.csv | B14: LandmarkAnchor_1 シートの元CSV。
A15: pilot_manual_review.csv | B15: BacklogReview_718 シートの元CSV。
A16: pilot_japan_2020_2025.csv | B16: 日本のみの主軸データ(pilot_east_asia_2020_2025.csvの日本分と同一内容)。
A17: codebook.md | B17: コーディング基準の全定義(争点区分・発話者レベル・Kingdon三次元・謝罪語彙6項目等)。
A18: pilot_coverage_report.md | B18: 収集・コーディング手法、交絡チェックの全過程を記録した作業ログ(このデータブックの元)。
A19: draft_paper_ja.md / draft_paper_ja.docx | B19: 本データに基づく論文ドラフト(『法政論叢』投稿用)。
A20: scripts/phase2_keyness_analysis.py | B20: Summary_Statsシートのキーネス分析表を生成したスクリプト。
A22: 主要列の定義(codebook.mdより抜粋)
A23: record_id | B23: レコード一意識別子(UUID)。
A24: country | B24: japan / korea / china。
A25: speaker_level | B25: HEAD(首脳:大統領・首相・国家主席)/ MINISTER(外務大臣級)/ OFFICIAL(報道官等の実務レベル)/ UNKNOWN(第三者的報道等)。
A26: document_type | B26: STATEMENT / PRESS_CONFERENCE / SPEECH / JOINT_STATEMENT / WRITTEN_RESPONSE / OTHER。
A27: issue_primary | B27: WAR_GENERAL / AGGRESSION / COLONIAL_RULE / COMFORT_WOMEN / SEXUAL_SLAVERY / NANJING / YASUKUNI / HISTORY_TEXTBOOK / FORCED_LABOR / COMPENSATION_REPARATION / APOLOGY_GENERAL / HISTORICAL_RECOGNITION_GENERAL / OTHER。
A28: kingdon_problem / kingdon_policy / kingdon_politics | B28: Kingdonの政策の窓モデルの三次元。当該発話がその次元に該当するか(0/1)。
A29: apology / explanation / remorse / reflection / remedy / pardon_or_forgiveness | B29: 謝罪関連語彙6項目(0/1)。全文読解に基づき判定、キーワード一致のみでは判定しない。
A30: responsibility_actor | B30: STATE / GOVERNMENT / LEADER / MILITARY / PEOPLE_NATION / UNSPECIFIED / OTHER / NA。
A31: agency_explicit | B31: 行為主体(誰が加害したか)が明示されているか(0/1、日本に一切言及しない発話はNA)。
A32: classification_confidence | B32: HIGH / MEDIUM / LOW。一次資料への直接アクセスが失敗し通信社報道で代替した記録はMEDIUM。
A33: coder_notes | B33: コーディング根拠・出典・留保事項を記した自由記述(すべての境界事例の判断根拠を含む)。
A34: source_url / archive_url | B34: 一次資料のURL。ライブサイトが遮断されている場合はarchive_urlにWayback Machineスナップショットを記録。
A36: コーディング方針の要点
A37: ・非ハルシネーション原則:実際にダウンロード・全文読解した文書のみを記録。判定不能な項目はUNKNOWN/NAとし、推測で埋めない。
A38: ・対外発信用の英語公式文書のみを対象(各国国内向け原語言説は対象外)。
A39: ・日本:首相官邸(kantei.go.jp)アーカイブの網羅的クロール+外務省(mofa.go.jp、ライブ遮断のためWayback Machine経由)のMINISTER級4件。
A40: ・韓国・中国:サイト構造上の制約(JS動的読み込み、アーカイブの遡及範囲上限等)により、目的的サンプリング(比較政治学の構造化・焦点化比較の枠組みで正当化)。
A41: ・一部のKorea/China記録は、一次資料への直接アクセスが繰り返し失敗した場合に限り、一次資料を直接引用する通信社報道で代替(classification_confidence=MEDIUMに格下げ、coder_notesに明記)。

Sheet Summary_Stats
A1: 集計サマリー(すべて MainAxis_101 シートを参照する数式。データを追加・修正すると自動再計算される)
A2: 注:このシートの数式はExcelで開くと自動的に計算されます(この作業環境ではLibreOfficeの自動計算が機能しないため、ここでは事前計算していません)。数式のロジックはpilot_east_asia_2020_2025.csvに対する独立したPython集計と突き合わせて確認済みです(日本agency_explicit=0.0%、韓国71.4%、中国86.7%など、draft_paper_ja.mdの数値と一致)。
A4: 1. 国別 謝罪関連語彙6項目・行為主体明示率
A5: draft_paper_ja.md 6節(三)(四)の表に対応。agency_explicitのみNA(欠損)を分母から除外。
A6: 国 | B6: n | C6: apology | D6: explanation | E6: remorse | F6: reflection | G6: remedy | H6: pardon_or_forgiveness | I6: agency_explicit(NA除く)
A7: 日本 | B7: =COUNTIF('MainAxis_101'!$B$2:$B$102,"japan") | C7: =COUNTIFS('MainAxis_101'!$B$2:$B$102,"japan",'MainAxis_101'!$T$2:$T$102,"1")/COUNTIF('MainAxis_101'!$B$2:$B$102,"japan") | D7: =COUNTIFS('MainAxis_101'!$B$2:$B$102,"japan",'MainAxis_101'!$U$2:$U$102,"1")/COUNTIF('MainAxis_101'!$B$2:$B$102,"japan") | E7: =COUNTIFS('MainAxis_101'!$B$2:$B$102,"japan",'MainAxis_101'!$V$2:$V$102,"1")/COUNTIF('MainAxis_101'!$B$2:$B$102,"japan") | F7: =COUNTIFS('MainAxis_101'!$B$2:$B$102,"japan",'MainAxis_101'!$W$2:$W$102,"1")/COUNTIF('MainAxis_101'!$B$2:$B$102,"japan") | G7: =COUNTIFS('MainAxis_101'!$B$2:$B$102,"japan",'MainAxis_101'!$X$2:$X$102,"1")/COUNTIF('MainAxis_101'!$B$2:$B$102,"japan") | H7: =COUNTIFS('MainAxis_101'!$B$2:$B$102,"japan",'MainAxis_101'!$Y$2:$Y$102,"1")/COUNTIF('MainAxis_101'!$B$2:$B$102,"japan") | I7: =COUNTIFS('MainAxis_101'!$B$2:$B$102,"japan",'MainAxis_101'!$AA$2:$AA$102,"1")/COUNTIFS('MainAxis_101'!$B$2:$B$102,"japan",'MainAxis_101'!$AA$2:$AA$102,"<>NA")
A8: 韓国 | B8: =COUNTIF('MainAxis_101'!$B$2:$B$102,"korea") | C8: =COUNTIFS('MainAxis_101'!$B$2:$B$102,"korea",'MainAxis_101'!$T$2:$T$102,"1")/COUNTIF('MainAxis_101'!$B$2:$B$102,"korea") | D8: =COUNTIFS('MainAxis_101'!$B$2:$B$102,"korea",'MainAxis_101'!$U$2:$U$102,"1")/COUNTIF('MainAxis_101'!$B$2:$B$102,"korea") | E8: =COUNTIFS('MainAxis_101'!$B$2:$B$102,"korea",'MainAxis_101'!$V$2:$V$102,"1")/COUNTIF('MainAxis_101'!$B$2:$B$102,"korea") | F8: =COUNTIFS('MainAxis_101'!$B$2:$B$102,"korea",'MainAxis_101'!$W$2:$W$102,"1")/COUNTIF('MainAxis_101'!$B$2:$B$102,"korea") | G8: =COUNTIFS('MainAxis_101'!$B$2:$B$102,"korea",'MainAxis_101'!$X$2:$X$102,"1")/COUNTIF('MainAxis_101'!$B$2:$B$102,"korea") | H8: =COUNTIFS('MainAxis_101'!$B$2:$B$102,"korea",'MainAxis_101'!$Y$2:$Y$102,"1")/COUNTIF('MainAxis_101'!$B$2:$B$102,"korea") | I8: =COUNTIFS('MainAxis_101'!$B$2:$B$102,"korea",'MainAxis_101'!$AA$2:$AA$102,"1")/COUNTIFS('MainAxis_101'!$B$2:$B$102,"korea",'MainAxis_101'!$AA$2:$AA$102,"<>NA")
A9: 中国 | B9: =COUNTIF('MainAxis_101'!$B$2:$B$102,"china") | C9: =COUNTIFS('MainAxis_101'!$B$2:$B$102,"china",'MainAxis_101'!$T$2:$T$102,"1")/COUNTIF('MainAxis_101'!$B$2:$B$102,"china") | D9: =COUNTIFS('MainAxis_101'!$B$2:$B$102,"china",'MainAxis_101'!$U$2:$U$102,"1")/COUNTIF('MainAxis_101'!$B$2:$B$102,"china") | E9: =COUNTIFS('MainAxis_101'!$B$2:$B$102,"china",'MainAxis_101'!$V$2:$V$102,"1")/COUNTIF('MainAxis_101'!$B$2:$B$102,"china") | F9: =COUNTIFS('MainAxis_101'!$B$2:$B$102,"china",'MainAxis_101'!$W$2:$W$102,"1")/COUNTIF('MainAxis_101'!$B$2:$B$102,"china") | G9: =COUNTIFS('MainAxis_101'!$B$2:$B$102,"china",'MainAxis_101'!$X$2:$X$102,"1")/COUNTIF('MainAxis_101'!$B$2:$B$102,"china") | H9: =COUNTIFS('MainAxis_101'!$B$2:$B$102,"china",'MainAxis_101'!$Y$2:$Y$102,"1")/COUNTIF('MainAxis_101'!$B$2:$B$102,"china") | I9: =COUNTIFS('MainAxis_101'!$B$2:$B$102,"china",'MainAxis_101'!$AA$2:$AA$102,"1")/COUNTIFS('MainAxis_101'!$B$2:$B$102,"china",'MainAxis_101'!$AA$2:$AA$102,"<>NA")
A11: 2. 日本:発話者レベル別(HEAD=首脳 / MINISTER=外務大臣級)
A12: speaker_level | B12: n | C12: apology | D12: remorse | E12: reflection | F12: remedy | G12: agency_explicit
A13: HEAD | B13: =COUNTIFS('MainAxis_101'!$B$2:$B$102,"japan",'MainAxis_101'!$G$2:$G$102,"HEAD") | C13: =COUNTIFS('MainAxis_101'!$B$2:$B$102,"japan",'MainAxis_101'!$G$2:$G$102,"HEAD",'MainAxis_101'!$T$2:$T$102,"1")/COUNTIFS('MainAxis_101'!$B$2:$B$102,"japan",'MainAxis_101'!$G$2:$G$102,"HEAD") | D13: =COUNTIFS('MainAxis_101'!$B$2:$B$102,"japan",'MainAxis_101'!$G$2:$G$102,"HEAD",'MainAxis_101'!$V$2:$V$102,"1")/COUNTIFS('MainAxis_101'!$B$2:$B$102,"japan",'MainAxis_101'!$G$2:$G$102,"HEAD") | E13: =COUNTIFS('MainAxis_101'!$B$2:$B$102,"japan",'MainAxis_101'!$G$2:$G$102,"HEAD",'MainAxis_101'!$W$2:$W$102,"1")/COUNTIFS('MainAxis_101'!$B$2:$B$102,"japan",'MainAxis_101'!$G$2:$G$102,"HEAD") | F13: =COUNTIFS('MainAxis_101'!$B$2:$B$102,"japan",'MainAxis_101'!$G$2:$G$102,"HEAD",'MainAxis_101'!$X$2:$X$102,"1")/COUNTIFS('MainAxis_101'!$B$2:$B$102,"japan",'MainAxis_101'!$G$2:$G$102,"HEAD") | G13: =COUNTIFS('MainAxis_101'!$B$2:$B$102,"japan",'MainAxis_101'!$G$2:$G$102,"HEAD",'MainAxis_101'!$AA$2:$AA$102,"1")/COUNTIFS('MainAxis_101'!$B$2:$B$102,"japan",'MainAxis_101'!$G$2:$G$102,"HEAD")
A14: MINISTER | B14: =COUNTIFS('MainAxis_101'!$B$2:$B$102,"japan",'MainAxis_101'!$G$2:$G$102,"MINISTER") | C14: =COUNTIFS('MainAxis_101'!$B$2:$B$102,"japan",'MainAxis_101'!$G$2:$G$102,"MINISTER",'MainAxis_101'!$T$2:$T$102,"1")/COUNTIFS('MainAxis_101'!$B$2:$B$102,"japan",'MainAxis_101'!$G$2:$G$102,"MINISTER") | D14: =COUNTIFS('MainAxis_101'!$B$2:$B$102,"japan",'MainAxis_101'!$G$2:$G$102,"MINISTER",'MainAxis_101'!$V$2:$V$102,"1")/COUNTIFS('MainAxis_101'!$B$2:$B$102,"japan",'MainAxis_101'!$G$2:$G$102,"MINISTER") | E14: =COUNTIFS('MainAxis_101'!$B$2:$B$102,"japan",'MainAxis_101'!$G$2:$G$102,"MINISTER",'MainAxis_101'!$W$2:$W$102,"1")/COUNTIFS('MainAxis_101'!$B$2:$B$102,"japan",'MainAxis_101'!$G$2:$G$102,"MINISTER") | F14: =COUNTIFS('MainAxis_101'!$B$2:$B$102,"japan",'MainAxis_101'!$G$2:$G$102,"MINISTER",'MainAxis_101'!$X$2:$X$102,"1")/COUNTIFS('MainAxis_101'!$B$2:$B$102,"japan",'MainAxis_101'!$G$2:$G$102,"MINISTER") | G14: =COUNTIFS('MainAxis_101'!$B$2:$B$102,"japan",'MainAxis_101'!$G$2:$G$102,"MINISTER",'MainAxis_101'!$AA$2:$AA$102,"1")/COUNTIFS('MainAxis_101'!$B$2:$B$102,"japan",'MainAxis_101'!$G$2:$G$102,"MINISTER")
A16: 3. 韓国:発話者レベル別 agency_explicit明示率
A17: speaker_level | B17: n | C17: agency_explicit
A18: HEAD | B18: =COUNTIFS('MainAxis_101'!$B$2:$B$102,"korea",'MainAxis_101'!$G$2:$G$102,"HEAD",'MainAxis_101'!$AA$2:$AA$102,"<>NA") | C18: =COUNTIFS('MainAxis_101'!$B$2:$B$102,"korea",'MainAxis_101'!$G$2:$G$102,"HEAD",'MainAxis_101'!$AA$2:$AA$102,"1")/COUNTIFS('MainAxis_101'!$B$2:$B$102,"korea",'MainAxis_101'!$G$2:$G$102,"HEAD",'MainAxis_101'!$AA$2:$AA$102,"<>NA")
A19: OFFICIAL | B19: =COUNTIFS('MainAxis_101'!$B$2:$B$102,"korea",'MainAxis_101'!$G$2:$G$102,"OFFICIAL",'MainAxis_101'!$AA$2:$AA$102,"<>NA") | C19: =COUNTIFS('MainAxis_101'!$B$2:$B$102,"korea",'MainAxis_101'!$G$2:$G$102,"OFFICIAL",'MainAxis_101'!$AA$2:$AA$102,"1")/COUNTIFS('MainAxis_101'!$B$2:$B$102,"korea",'MainAxis_101'!$G$2:$G$102,"OFFICIAL",'MainAxis_101'!$AA$2:$AA$102,"<>NA")
A21: 3b. 韓国:大統領(HEAD)級 agency_explicit明示率、政権別
A22: 大統領(政権) | B22: n(NA除く) | C22: agency_explicit
A23: Moon Jae-in | B23: =COUNTIFS('MainAxis_101'!$B$2:$B$102,"korea",'MainAxis_101'!$E$2:$E$102,"Moon Jae-in",'MainAxis_101'!$AA$2:$AA$102,"<>NA") | C23: =COUNTIFS('MainAxis_101'!$B$2:$B$102,"korea",'MainAxis_101'!$E$2:$E$102,"Moon Jae-in",'MainAxis_101'!$AA$2:$AA$102,"1")/COUNTIFS('MainAxis_101'!$B$2:$B$102,"korea",'MainAxis_101'!$E$2:$E$102,"Moon Jae-in",'MainAxis_101'!$AA$2:$AA$102,"<>NA")
A24: Yoon Suk Yeol | B24: =COUNTIFS('MainAxis_101'!$B$2:$B$102,"korea",'MainAxis_101'!$E$2:$E$102,"Yoon Suk Yeol",'MainAxis_101'!$AA$2:$AA$102,"<>NA") | C24: =COUNTIFS('MainAxis_101'!$B$2:$B$102,"korea",'MainAxis_101'!$E$2:$E$102,"Yoon Suk Yeol",'MainAxis_101'!$AA$2:$AA$102,"1")/COUNTIFS('MainAxis_101'!$B$2:$B$102,"korea",'MainAxis_101'!$E$2:$E$102,"Yoon Suk Yeol",'MainAxis_101'!$AA$2:$AA$102,"<>NA")
A25: Lee Jae Myung | B25: =COUNTIFS('MainAxis_101'!$B$2:$B$102,"korea",'MainAxis_101'!$E$2:$E$102,"Lee Jae Myung",'MainAxis_101'!$AA$2:$AA$102,"<>NA") | C25: =COUNTIFS('MainAxis_101'!$B$2:$B$102,"korea",'MainAxis_101'!$E$2:$E$102,"Lee Jae Myung",'MainAxis_101'!$AA$2:$AA$102,"1")/COUNTIFS('MainAxis_101'!$B$2:$B$102,"korea",'MainAxis_101'!$E$2:$E$102,"Lee Jae Myung",'MainAxis_101'!$AA$2:$AA$102,"<>NA")
A27: 4. 中国:発話者レベル別 agency_explicit明示率
A28: speaker_level | B28: n | C28: agency_explicit
A29: HEAD | B29: =COUNTIFS('MainAxis_101'!$B$2:$B$102,"china",'MainAxis_101'!$G$2:$G$102,"HEAD") | C29: =COUNTIFS('MainAxis_101'!$B$2:$B$102,"china",'MainAxis_101'!$G$2:$G$102,"HEAD",'MainAxis_101'!$AA$2:$AA$102,"1")/COUNTIFS('MainAxis_101'!$B$2:$B$102,"china",'MainAxis_101'!$G$2:$G$102,"HEAD")
A30: OFFICIAL | B30: =COUNTIFS('MainAxis_101'!$B$2:$B$102,"china",'MainAxis_101'!$G$2:$G$102,"OFFICIAL") | C30: =COUNTIFS('MainAxis_101'!$B$2:$B$102,"china",'MainAxis_101'!$G$2:$G$102,"OFFICIAL",'MainAxis_101'!$AA$2:$AA$102,"1")/COUNTIFS('MainAxis_101'!$B$2:$B$102,"china",'MainAxis_101'!$G$2:$G$102,"OFFICIAL")
A31: UNKNOWN | B31: =COUNTIFS('MainAxis_101'!$B$2:$B$102,"china",'MainAxis_101'!$G$2:$G$102,"UNKNOWN") | C31: =COUNTIFS('MainAxis_101'!$B$2:$B$102,"china",'MainAxis_101'!$G$2:$G$102,"UNKNOWN",'MainAxis_101'!$AA$2:$AA$102,"1")/COUNTIFS('MainAxis_101'!$B$2:$B$102,"china",'MainAxis_101'!$G$2:$G$102,"UNKNOWN")
A33: 5. Kingdon三次元(問題・政策・政治)への該当率、国別
A34: 国 | B34: n | C34: kingdon_problem | D34: kingdon_policy | E34: kingdon_politics
A35: 日本 | B35: =COUNTIF('MainAxis_101'!$B$2:$B$102,"japan") | C35: =COUNTIFS('MainAxis_101'!$B$2:$B$102,"japan",'MainAxis_101'!$P$2:$P$102,"1")/COUNTIF('MainAxis_101'!$B$2:$B$102,"japan") | D35: =COUNTIFS('MainAxis_101'!$B$2:$B$102,"japan",'MainAxis_101'!$Q$2:$Q$102,"1")/COUNTIF('MainAxis_101'!$B$2:$B$102,"japan") | E35: =COUNTIFS('MainAxis_101'!$B$2:$B$102,"japan",'MainAxis_101'!$R$2:$R$102,"1")/COUNTIF('MainAxis_101'!$B$2:$B$102,"japan")
A36: 韓国 | B36: =COUNTIF('MainAxis_101'!$B$2:$B$102,"korea") | C36: =COUNTIFS('MainAxis_101'!$B$2:$B$102,"korea",'MainAxis_101'!$P$2:$P$102,"1")/COUNTIF('MainAxis_101'!$B$2:$B$102,"korea") | D36: =COUNTIFS('MainAxis_101'!$B$2:$B$102,"korea",'MainAxis_101'!$Q$2:$Q$102,"1")/COUNTIF('MainAxis_101'!$B$2:$B$102,"korea") | E36: =COUNTIFS('MainAxis_101'!$B$2:$B$102,"korea",'MainAxis_101'!$R$2:$R$102,"1")/COUNTIF('MainAxis_101'!$B$2:$B$102,"korea")
A37: 中国 | B37: =COUNTIF('MainAxis_101'!$B$2:$B$102,"china") | C37: =COUNTIFS('MainAxis_101'!$B$2:$B$102,"china",'MainAxis_101'!$P$2:$P$102,"1")/COUNTIF('MainAxis_101'!$B$2:$B$102,"china") | D37: =COUNTIFS('MainAxis_101'!$B$2:$B$102,"china",'MainAxis_101'!$Q$2:$Q$102,"1")/COUNTIF('MainAxis_101'!$B$2:$B$102,"china") | E37: =COUNTIFS('MainAxis_101'!$B$2:$B$102,"china",'MainAxis_101'!$R$2:$R$102,"1")/COUNTIF('MainAxis_101'!$B$2:$B$102,"china")
A39: 6. issue_primary(争点)分布、国別
A40: issue_primary | B40: 日本 | C40: 韓国 | D40: 中国
A41: WAR_GENERAL | B41: =COUNTIFS('MainAxis_101'!$B$2:$B$102,"japan",'MainAxis_101'!$N$2:$N$102,"WAR_GENERAL") | C41: =COUNTIFS('MainAxis_101'!$B$2:$B$102,"korea",'MainAxis_101'!$N$2:$N$102,"WAR_GENERAL") | D41: =COUNTIFS('MainAxis_101'!$B$2:$B$102,"china",'MainAxis_101'!$N$2:$N$102,"WAR_GENERAL")
A42: AGGRESSION | B42: =COUNTIFS('MainAxis_101'!$B$2:$B$102,"japan",'MainAxis_101'!$N$2:$N$102,"AGGRESSION") | C42: =COUNTIFS('MainAxis_101'!$B$2:$B$102,"korea",'MainAxis_101'!$N$2:$N$102,"AGGRESSION") | D42: =COUNTIFS('MainAxis_101'!$B$2:$B$102,"china",'MainAxis_101'!$N$2:$N$102,"AGGRESSION")
A43: COLONIAL_RULE | B43: =COUNTIFS('MainAxis_101'!$B$2:$B$102,"japan",'MainAxis_101'!$N$2:$N$102,"COLONIAL_RULE") | C43: =COUNTIFS('MainAxis_101'!$B$2:$B$102,"korea",'MainAxis_101'!$N$2:$N$102,"COLONIAL_RULE") | D43: =COUNTIFS('MainAxis_101'!$B$2:$B$102,"china",'MainAxis_101'!$N$2:$N$102,"COLONIAL_RULE")
A44: COMFORT_WOMEN | B44: =COUNTIFS('MainAxis_101'!$B$2:$B$102,"japan",'MainAxis_101'!$N$2:$N$102,"COMFORT_WOMEN") | C44: =COUNTIFS('MainAxis_101'!$B$2:$B$102,"korea",'MainAxis_101'!$N$2:$N$102,"COMFORT_WOMEN") | D44: =COUNTIFS('MainAxis_101'!$B$2:$B$102,"china",'MainAxis_101'!$N$2:$N$102,"COMFORT_WOMEN")
A45: SEXUAL_SLAVERY | B45: =COUNTIFS('MainAxis_101'!$B$2:$B$102,"japan",'MainAxis_101'!$N$2:$N$102,"SEXUAL_SLAVERY") | C45: =COUNTIFS('MainAxis_101'!$B$2:$B$102,"korea",'MainAxis_101'!$N$2:$N$102,"SEXUAL_SLAVERY") | D45: =COUNTIFS('MainAxis_101'!$B$2:$B$102,"china",'MainAxis_101'!$N$2:$N$102,"SEXUAL_SLAVERY")
A46: NANJING | B46: =COUNTIFS('MainAxis_101'!$B$2:$B$102,"japan",'MainAxis_101'!$N$2:$N$102,"NANJING") | C46: =COUNTIFS('MainAxis_101'!$B$2:$B$102,"korea",'MainAxis_101'!$N$2:$N$102,"NANJING") | D46: =COUNTIFS('MainAxis_101'!$B$2:$B$102,"china",'MainAxis_101'!$N$2:$N$102,"NANJING")
A47: YASUKUNI | B47: =COUNTIFS('MainAxis_101'!$B$2:$B$102,"japan",'MainAxis_101'!$N$2:$N$102,"YASUKUNI") | C47: =COUNTIFS('MainAxis_101'!$B$2:$B$102,"korea",'MainAxis_101'!$N$2:$N$102,"YASUKUNI") | D47: =COUNTIFS('MainAxis_101'!$B$2:$B$102,"china",'MainAxis_101'!$N$2:$N$102,"YASUKUNI")
A48: HISTORY_TEXTBOOK | B48: =COUNTIFS('MainAxis_101'!$B$2:$B$102,"japan",'MainAxis_101'!$N$2:$N$102,"HISTORY_TEXTBOOK") | C48: =COUNTIFS('MainAxis_101'!$B$2:$B$102,"korea",'MainAxis_101'!$N$2:$N$102,"HISTORY_TEXTBOOK") | D48: =COUNTIFS('MainAxis_101'!$B$2:$B$102,"china",'MainAxis_101'!$N$2:$N$102,"HISTORY_TEXTBOOK")
A49: FORCED_LABOR | B49: =COUNTIFS('MainAxis_101'!$B$2:$B$102,"japan",'MainAxis_101'!$N$2:$N$102,"FORCED_LABOR") | C49: =COUNTIFS('MainAxis_101'!$B$2:$B$102,"korea",'MainAxis_101'!$N$2:$N$102,"FORCED_LABOR") | D49: =COUNTIFS('MainAxis_101'!$B$2:$B$102,"china",'MainAxis_101'!$N$2:$N$102,"FORCED_LABOR")
A50: COMPENSATION_REPARATION | B50: =COUNTIFS('MainAxis_101'!$B$2:$B$102,"japan",'MainAxis_101'!$N$2:$N$102,"COMPENSATION_REPARATION") | C50: =COUNTIFS('MainAxis_101'!$B$2:$B$102,"korea",'MainAxis_101'!$N$2:$N$102,"COMPENSATION_REPARATION") | D50: =COUNTIFS('MainAxis_101'!$B$2:$B$102,"china",'MainAxis_101'!$N$2:$N$102,"COMPENSATION_REPARATION")
A51: APOLOGY_GENERAL | B51: =COUNTIFS('MainAxis_101'!$B$2:$B$102,"japan",'MainAxis_101'!$N$2:$N$102,"APOLOGY_GENERAL") | C51: =COUNTIFS('MainAxis_101'!$B$2:$B$102,"korea",'MainAxis_101'!$N$2:$N$102,"APOLOGY_GENERAL") | D51: =COUNTIFS('MainAxis_101'!$B$2:$B$102,"china",'MainAxis_101'!$N$2:$N$102,"APOLOGY_GENERAL")
A52: HISTORICAL_RECOGNITION_GENERAL | B52: =COUNTIFS('MainAxis_101'!$B$2:$B$102,"japan",'MainAxis_101'!$N$2:$N$102,"HISTORICAL_RECOGNITION_GENERAL") | C52: =COUNTIFS('MainAxis_101'!$B$2:$B$102,"korea",'MainAxis_101'!$N$2:$N$102,"HISTORICAL_RECOGNITION_GENERAL") | D52: =COUNTIFS('MainAxis_101'!$B$2:$B$102,"china",'MainAxis_101'!$N$2:$N$102,"HISTORICAL_RECOGNITION_GENERAL")
A53: OTHER | B53: =COUNTIFS('MainAxis_101'!$B$2:$B$102,"japan",'MainAxis_101'!$N$2:$N$102,"OTHER") | C53: =COUNTIFS('MainAxis_101'!$B$2:$B$102,"korea",'MainAxis_101'!$N$2:$N$102,"OTHER") | D53: =COUNTIFS('MainAxis_101'!$B$2:$B$102,"china",'MainAxis_101'!$N$2:$N$102,"OTHER")
A54: 合計 | B54: =COUNTIF('MainAxis_101'!$B$2:$B$102,"japan") | C54: =COUNTIF('MainAxis_101'!$B$2:$B$102,"korea") | D54: =COUNTIF('MainAxis_101'!$B$2:$B$102,"china")
A56: 7. キーネス分析(対数尤度比 LL)上位10語、国別
A57: 注:この表はスプレッドシート数式では再現できない(全文トークン化+対数尤度比計算が必要)。scripts/phase2_keyness_analysis.py を pilot_east_asia_2020_2025.csv(101件)+landmark_anchors.csv(1件)に対して2026-09-23に再実行した結果を、確認済みの固定値としてここに転記したもの。再現するには同スクリプトを再実行すること。
A58: 順位 | B58: 日本(総語数9,413) | C58: LL | D58: 韓国(総語数9,392) | E58: LL | F58: 中国(総語数3,836) | G58: LL
A59: 1 | B59: atomic | C59: 273.3 | D59: korea | E59: 199.3 | F59: china | G59: 217
A60: 2 | B60: nuclear | C60: 248.7 | D60: freedom | E60: 148.4 | F60: chinese | G60: 213
A61: 3 | B61: bomb | C61: 175.5 | D61: independence | E61: 105.1 | F61: aggression | G61: 149.2
A62: 4 | B62: weapons | C62: 139.2 | D62: korean | E62: 79.6 | F62: nanjing | G62: 127.8
A63: 5 | B63: prime | C63: 132.6 | D63: liberation | E63: 68.9 | F63: japanese | G63: 115.6
A64: 6 | B64: hiroshima | C64: 101.4 | D64: koreans | E64: 67.2 | F64: war | G64: 93.9
A65: 7 | B65: nagasaki | C65: 98.3 | D65: government | E65: 57.6 | F65: massacre | G65: 95.9
A66: 8 | B66: minister | C66: 95.9 | D66: movement | E66: 54.6 | F66: shrine | G66: 90.9
A67: 9 | B67: dead | C67: 84.2 | D67: north | E67: 48.7 | F67: resistance | G67: 77.2
A68: 10 | B68: heartfelt | C68: 79 | D68: fellow | E68: 48.4 | F68: yasukuni | G68: 67.5
A70: 出典・関連ファイル: pilot_coverage_report.md(手法の全文)、draft_paper_ja.md 6節(この表の解釈)。

Sheet Sources_102
A1: この一覧は、主軸コーパス101件+歴史的画期1件、計102件それぞれについて、本文を取得した一次資料URL(および、ライブサイト遮断時にWayback Machine等で代替取得した場合はそのアーカイブURL)を記載したもの。個々のレコードの詳細(response_text全文・coder_notes等)は MainAxis_101 / LandmarkAnchor_1 シートを参照。
A3: No. | B3: 国 | C3: 日付 | D3: 発話者 | E3: 発話者レベル | F3: 文書種別 | G3: 文書タイトル | H3: 一次資料URL | I3: アーカイブURL(Wayback等) | J3: 取得日 | K3: 収集方法 | L3: 確度 | M3: 区分
A4: 1 | B4: 中国 | C4: 2020-09-18 | D4: UNKNOWN | E4: UNKNOWN | F4: OTHER | G4: China commemorates 89th anniversary of the September 18 Incident | H4: https://news.cgtn.com/news/2020-09-18/Shenyang-commemorates-89th-anniversary-of-September-18-Incident--TSGXoRLqhy/index.html | J4: 2026-09-22 | K4: GOVCN_NEWS_ARCHIVE_WEB_SEARCH | L4: HIGH
A5: 2 | B5: 中国 | C5: 2021-07-07 | D5: UNKNOWN | E5: UNKNOWN | F5: OTHER | G5: China commemorates 84th anniversary of the Lugou (Marco Polo) Bridge Incident | H5: https://www.globaltimes.cn/page/202107/1228040.shtml | J5: 2026-09-22 | K5: GOVCN_NEWS_ARCHIVE_WEB_SEARCH | L5: HIGH
A6: 3 | B6: 中国 | C6: 2021-08-15 | D6: Hua Chunying | E6: OFFICIAL | F6: PRESS_CONFERENCE | G6: Foreign Ministry Spokesperson Hua Chunying's Remarks on Yasukuni Shrine | H6: https://tl.china-embassy.gov.cn/eng/fyrth/202108/t20210815_8909776.htm | J6: 2026-09-22 | K6: MFA_CHINA_DIRECT_FETCH_WEB_SEARCH | L6: HIGH
A7: 4 | B7: 中国 | C7: 2021-12-13 | D7: UNKNOWN | E7: UNKNOWN | F7: OTHER | G7: China holds national memorial ceremony for Nanjing Massacre victims (eighth) | H7: https://english.www.gov.cn/news/topnews/202112/13/content_WS61b6e2c1c6d09c94e48a2271.html | J7: 2026-09-22 | K7: GOVCN_NEWS_ARCHIVE_WEB_SEARCH | L7: HIGH
A8: 5 | B8: 中国 | C8: 2022-08-14 | D8: Wang Wenbin | E8: OFFICIAL | F8: PRESS_CONFERENCE | G8: Foreign Ministry Spokesperson Wang Wenbin's Remarks on Yasukuni Shrine | H8: https://www.fmprc.gov.cn/eng./xw/fyrbt/fyrbt/202405/t20240530_11349753.html | J8: 2026-09-22 | K8: MFA_CHINA_DIRECT_FETCH_WEB_SEARCH | L8: HIGH
A9: 6 | B9: 中国 | C9: 2022-08-15 | D9: Wang Wenbin | E9: OFFICIAL | F9: PRESS_CONFERENCE | G9: Foreign Ministry Spokesperson Wang Wenbin's Regular Press Conference on August 15, 2022 | H9: https://www.mfa.gov.cn/eng/xw/fyrbt/lxjzh/202405/t20240530_11347346.html | J9: 2026-09-22 | K9: MANUAL_TARGETED_DATE_SEARCH | L9: HIGH
A10: 7 | B10: 中国 | C10: 2022-11-17 | D10: Xi Jinping | E10: HEAD | F10: OTHER | G10: President Xi Jinping Meets with Japanese Prime Minister Fumio Kishida (Bangkok, APEC) | H10: https://www.fmprc.gov.cn/mfa_eng/zy/jj/2022/cxesgjtytjhtg/202211/t20221118_10977309.html | J10: 2026-09-22 | K10: MFA_CHINA_DIRECT_FETCH_WEB_SEARCH | L10: MEDIUM
A11: 8 | B11: 中国 | C11: 2022-12-13 | D11: UNKNOWN | E11: UNKNOWN | F11: OTHER | G11: China holds national memorial ceremony for Nanjing Massacre victims (ninth) | H11: https://english.www.gov.cn/news/topnews/202212/13/content_WS6397f285c6d0a757729e467f.html | J11: 2026-09-22 | K11: GOVCN_NEWS_ARCHIVE_WEB_SEARCH | L11: HIGH
A12: 9 | B12: 中国 | C12: 2023-07-07 | D12: UNKNOWN | E12: UNKNOWN | F12: OTHER | G12: China commemorates 86th anniversary of the Lugou (Marco Polo) Bridge Incident | H12: https://news.cgtn.com/news/2023-07-07/Remembering-Lugou-Bridge-Incident-and-Japan-s-war-crimes-1lfs1zncJTa/index.html | J12: 2026-09-22 | K12: GOVCN_NEWS_ARCHIVE_WEB_SEARCH | L12: HIGH
A13: 10 | B13: 中国 | C13: 2023-09-18 | D13: UNKNOWN | E13: UNKNOWN | F13: OTHER | G13: China commemorates 92nd anniversary of the September 18 Incident | H13: https://english.www.gov.cn/news/202309/18/content_WS65090967c6d0868f4e8df8f7.html | J13: 2026-09-22 | K13: GOVCN_NEWS_ARCHIVE_WEB_SEARCH | L13: HIGH
A14: 11 | B14: 中国 | C14: 2023-10-17 | D14: Mao Ning | E14: OFFICIAL | F14: PRESS_CONFERENCE | G14: Foreign Ministry Spokesperson Mao Ning’s Regular Press Conference on October 17, 2023_Ministry of Foreign Affairs of the People's Republic of China | H14: https://www.mfa.gov.cn/eng/xw/fyrbt/lxjzh/202405/t20240530_11347616.html | J14: NA | K14: (直接クロール、パイプライン01-09段階) | L14: HIGH
A15: 12 | B15: 中国 | C15: 2023-11-16 | D15: Xi Jinping | E15: HEAD | F15: OTHER | G15: Xi meets Kishida, reaffirming strategic and mutually beneficial relations (San Francisco, APEC) | H15: https://www.globaltimes.cn/page/202311/1302045.shtml | J15: 2026-09-22 | K15: MFA_CHINA_DIRECT_FETCH_WEB_SEARCH | L15: MEDIUM
... A33: 30 | B33: 中国 | C33: 2026-08-15 | D33: MOFA Spokesperson | E33: OFFICIAL | F33: OTHER | G33: Explainer: Yasukuni is a shrine for Japanese war criminals (Xinhua, quoting MOFA reaction to Aug 2026 visits) | H33: https://english.news.cn/20260819/ccc6afb34e874620bf95fd1bf57c8d7f/c.html | J33: 2026-09-22 | K33: WIRE_SERVICE_QUOTE_WEB_SEARCH | L33: MEDIUM
A34: 31 | B34: 日本 | C34: 1995-08-15 | D34: MURAYAMA Tomiichi | E34: HEAD | F34: STATEMENT | G34: Statement by Prime Minister Tomiichi Murayama "On the occasion of the 50th anniversary of the war's end" (15 August 1995) | H34: https://www.mofa.go.jp/announce/press/pm/murayama/9508.html | I34: https://web.archive.org/web/20260905165251/https://www.mofa.go.jp/announce/press/pm/murayama/9508.html | J34: 2026-09-22 | K34: WAYBACK_MANUAL_LANDMARK_ANCHOR | L34: HIGH | M34: 歴史的画期
A35: 32 | B35: 日本 | C35: 2020-05-19 | D35: MOTEGI Toshimitsu | E35: MINISTER | F35: PRESS_CONFERENCE | G35: Press Conference by Foreign Minister MOTEGI Toshimitsu (May 19, 2020) | H35: https://www.mofa.go.jp/press/kaiken/kaiken4e_000798.html | I35: https://web.archive.org/web/20251108125333id_/https://www.mofa.go.jp/press/kaiken/kaiken4e_000798.html | J35: 2026-09-22 | K35: MOFA_JAPAN_WAYBACK_MACHINE_FETCH | L35: HIGH
A36: 33 | B36: 日本 | C36: 2020-06-23 | D36: ABE Shinzo | E36: HEAD | F36: SPEECH | G36: Address by the Prime Minister for the Memorial Ceremony to Commemorate the Fallen on the 75th Anniversary of the End of the Battle of Okinawa | H36: https://japan.kantei.go.jp/98_abe/statement/201906/_00005.html | J36: 2026-09-22 | K36: MANUAL_REVIEW_BACKLOG | L36: HIGH
A37: 34 | B37: 日本 | C37: 2020-08-06 | D37: ABE Shinzo | E37: HEAD | F37: SPEECH | G37: Address by the Prime Minister at the Hiroshima Peace Memorial Ceremony | H37: https://japan.kantei.go.jp/98_abe/statement/202008/_00001.html | J37: 2026-09-22 | K37: KANTEI_ARCHIVE_KEYWORD_BACKLOG_REVIEW | L37: HIGH
A38: 35 | B38: 日本 | C38: 2020-08-09 | D38: ABE Shinzo | E38: HEAD | F38: SPEECH | G38: Address by the Prime Minister at the Nagasaki Peace Memorial Ceremony | H38: https://japan.kantei.go.jp/98_abe/statement/202008/_00002.html | J38: 2026-09-22 | K38: KANTEI_ARCHIVE_KEYWORD_BACKLOG_REVIEW | L38: HIGH
A39: 36 | B39: 日本 | C39: 2020-08-15 | D39: ABE Shinzo | E39: HEAD | F39: SPEECH | G39: Address by the Prime Minister at the Seventy-Fifth National Memorial Ceremony for the War Dead (Speeches and Statements by the Prime Minister) | Prime Minister of Japan and His Cabinet | H39: https://japan.kantei.go.jp/98_abe/statement/202008/_00003.html | J39: NA | K39: (直接クロール、パイプライン01-09段階) | L39: MEDIUM
A40: 37 | B40: 日本 | C40: 2021-01-08 | D40: SUGA Yoshihide | E40: HEAD | F40: PRESS_CONFERENCE | G40: Press Conference by the Prime Minister on the court case brought by a group of former comfort women (Speeches and Statements by the Prime Minister) | Prime Minister of Japan and His Cabinet | H40: https://japan.kantei.go.jp/99_suga/statement/202101/_00004.html | J40: NA | K40: (直接クロール、パイプライン01-09段階) | L40: HIGH
A41: 38 | B41: 日本 | C41: 2021-06-23 | D41: SUGA Yoshihide | E41: HEAD | F41: SPEECH | G41: Address by the Prime Minister for the Memorial Ceremony to Commemorate the Fallen on the 76th Anniversary of the End of the Battle of Okinawa | H41: https://japan.kantei.go.jp/99_suga/statement/202106/_00010.html | J41: 2026-09-22 | K41: MANUAL_REVIEW_BACKLOG | L41: HIGH
A42: 39 | B42: 日本 | C42: 2021-08-06 | D42: SUGA Yoshihide | E42: HEAD | F42: SPEECH | G42: Address by the Prime Minister at the Hiroshima Peace Memorial Ceremony | H42: https://japan.kantei.go.jp/99_suga/statement/202108/_00003.html | J42: 2026-09-22 | K42: KANTEI_ARCHIVE_KEYWORD_BACKLOG_REVIEW | L42: HIGH
A43: 40 | B43: 日本 | C43: 2021-08-09 | D43: SUGA Yoshihide | E43: HEAD | F43: SPEECH | G43: Address by the Prime Minister at the Nagasaki Peace Memorial Ceremony | H43: https://japan.kantei.go.jp/99_suga/statement/202108/_00004.html | J43: 2026-09-22 | K43: KANTEI_ARCHIVE_KEYWORD_BACKLOG_REVIEW | L43: HIGH
A44: 41 | B44: 日本 | C44: 2021-08-15 | D44: SUGA Yoshihide | E44: HEAD | F44: SPEECH | G44: Address by the Prime Minister at the Seventy-Sixth National Memorial Ceremony for the War Dead (Speeches and Statements by the Prime Minister) | Prime Minister of Japan and His Cabinet | H44: https://japan.kantei.go.jp/99_suga/statement/202108/_00006.html | J44: NA | K44: (直接クロール、パイプライン01-09段階) | L44: MEDIUM
A45: 42 | B45: 日本 | C45: 2021-10-15 | D45: KISHIDA Fumio | E45: HEAD | F45: PRESS_CONFERENCE | G45: Press Conference by the Prime Minister regarding Japan-ROK Telephone Summit Talks | H45: https://japan.kantei.go.jp/100_kishida/statement/202110/_00013.html | J45: 2026-09-22 | K45: MANUAL_REVIEW_BACKLOG | L45: HIGH
A46: 43 | B46: 日本 | C46: 2022-01-28 | D46: KISHIDA Fumio | E46: HEAD | F46: PRESS_CONFERENCE | G46: Press Conference by the Prime Minister regarding the Status of Consideration toward the Inscription on the World Cultural Heritage List of the Sado Complex of Heritage Mines, Primarily Gold Mines | H46: https://japan.kantei.go.jp/101_kishida/statement/202201/_00015.html | J46: 2026-09-22 | K46: MANUAL_REVIEW_BACKLOG | L46: HIGH
A47: 44 | B47: 日本 | C47: 2022-03-11 | D47: KISHIDA Fumio | E47: HEAD | F47: PRESS_CONFERENCE | G47: Press Conference on the Telephone Talk with Mr. YOON Suk Yeol, President-elect of the Republic of Korea | H47: https://japan.kantei.go.jp/101_kishida/statement/202203/_00010.html | J47: 2026-09-22 | K47: MANUAL_REVIEW_BACKLOG | L47: MEDIUM
A48: 45 | B48: 日本 | C48: 2022-05-10 | D48: HAYASHI Yoshimasa | E48: MINISTER | F48: PRESS_CONFERENCE | G48: Extraordinary Press Conference by Foreign Minister HAYASHI Yoshimasa (May 10, 2022, 3:29 p.m., Seoul) | H48: https://www.mofa.go.jp/press/kaiken/kaiken22e_000078.html | I48: https://web.archive.org/web/20230306220010id_/https://www.mofa.go.jp/press/kaiken/kaiken22e_000078.html | J48: 2026-09-22 | K48: MOFA_JAPAN_WAYBACK_MACHINE_FETCH | L48: HIGH
A49: 46 | B49: 日本 | C49: 2022-06-10 | D49: KISHIDA Fumio | E49: HEAD | F49: PRESS_CONFERENCE | G49: Press Conference by the Prime Minister on His Keynote Address at the Shangri-La Dialogue (the IISS Asia Security Summit) and Other Matters | H49: https://japan.kantei.go.jp/101_kishida/statement/202206/_00005.html | J49: 2026-09-22 | K49: MANUAL_REVIEW_BACKLOG | L49: HIGH
A50: 47 | B50: 日本 | C50: 2022-08-06 | D50: KISHIDA Fumio | E50: HEAD | F50: SPEECH | G50: Address by Prime Minister KISHIDA Fumio at the Hiroshima Peace Memorial Ceremony | H50: https://japan.kantei.go.jp/101_kishida/statement/202208/_00003.html | J50: 2026-09-22 | K50: KANTEI_ARCHIVE_KEYWORD_BACKLOG_REVIEW | L50: HIGH
A51: 48 | B51: 日本 | C51: 2022-08-09 | D51: KISHIDA Fumio | E51: HEAD | F51: SPEECH | G51: Address by Prime Minister KISHIDA Fumio at the Nagasaki Peace Memorial Ceremony | H51: https://japan.kantei.go.jp/101_kishida/statement/202208/_00004.html | J51: 2026-09-22 | K51: KANTEI_ARCHIVE_KEYWORD_BACKLOG_REVIEW | L51: HIGH
A52: 49 | B52: 日本 | C52: 2022-08-10 | D52: HAYASHI Yoshimasa | E52: MINISTER | F52: PRESS_CONFERENCE | G52: Press Conference by Foreign Minister HAYASHI Yoshimasa (August 10, 2022, 8:11 p.m.) | H52: https://www.mofa.go.jp/press/kaiken/kaiken24e_000151.html | I52: https://web.archive.org/web/20251203124600id_/https://www.mofa.go.jp/press/kaiken/kaiken24e_000151.html | J52: 2026-09-22 | K52: MOFA_JAPAN_WAYBACK_MACHINE_FETCH | L52: HIGH
A53: 50 | B53: 日本 | C53: 2022-08-15 | D53: KISHIDA Fumio | E53: HEAD | F53: SPEECH | G53: Address by Prime Minister Kishida at the Seventy-Seventh National Memorial Ceremony for the War Dead (Speeches and Statements <br>by the Prime Minister) | Prime Minister's Office of Japan | H53: https://japan.kantei.go.jp/101_kishida/statement/202208/_00006.html | J53: NA | K53: (直接クロール、パイプライン01-09段階) | L53: MEDIUM
A54: 51 | B54: 日本 | C54: 2022-11-13 | D54: KISHIDA Fumio | E54: HEAD | F54: PRESS_CONFERENCE | G54: Press Conference by Prime Minister Kishida regarding the ASEAN-related Summit Meetings and Other Matters | H54: https://japan.kantei.go.jp/101_kishida/statement/202211/_00007.html | J54: 2026-09-22 | K54: MANUAL_REVIEW_BACKLOG | L54: HIGH
A55: 52 | B55: 日本 | C55: 2023-03-06 | D55: KISHIDA Fumio | E55: HEAD | F55: PRESS_CONFERENCE | G55: Press Conference by the Prime Minister regarding the Issue of Former Civilian Workers from the Korean Peninsula (Speeches and Statements <br>by the Prime Minister) | Prime Minister's Office of Japan | H55: https://japan.kantei.go.jp/101_kishida/statement/202303/_00004.html | J55: NA | K55: (直接クロール、パイプライン01-09段階) | L55: HIGH
A56: 53 | B56: 日本 | C56: 2023-03-16 | D56: KISHIDA Fumio | E56: HEAD | F56: PRESS_CONFERENCE | G56: Joint Press Conference by the Leaders of Japan and the Republic of Korea (Speeches and Statements <br>by the Prime Minister) | Prime Minister's Office of Japan | H56: https://japan.kantei.go.jp/101_kishida/statement/202303/_00010.html | J56: NA | K56: (直接クロール、パイプライン01-09段階) | L56: HIGH
A57: 54 | B57: 日本 | C57: 2023-05-07 | D57: KISHIDA Fumio | E57: HEAD | F57: PRESS_CONFERENCE | G57: Japanese Prime Minister: 'my heart hurts' over forced laborers' suffering | H57: https://eng.president.go.kr/briefing/EtDV6ERL | I57: https://web.archive.org/web/20241204144009id_/https://eng.president.go.kr/briefing/EtDV6ERL | J57: 2026-09-22 | K57: WAYBACK_CDX_KOREA_PRESIDENTIAL_BRIEFING | L57: MEDIUM
A58: 55 | B58: 日本 | C58: 2023-06-23 | D58: KISHIDA Fumio | E58: HEAD | F58: SPEECH | G58: Address by Prime Minister KISHIDA Fumio for the Memorial Ceremony to Commemorate the Fallen on the 78th Anniversary of the End of the Battle of Okinawa | H58: https://japan.kantei.go.jp/101_kishida/statement/202306/0623okinawa.html | J58: 2026-09-22 | K58: MANUAL_REVIEW_BACKLOG | L58: HIGH
A59: 56 | B59: 日本 | C59: 2023-08-06 | D59: KISHIDA Fumio | E59: HEAD | F59: SPEECH | G59: Address by Prime Minister KISHIDA Fumio at the Hiroshima Peace Memorial Ceremony | H59: https://japan.kantei.go.jp/101_kishida/statement/202308/06hiroshima.html | J59: 2026-09-22 | K59: KANTEI_ARCHIVE_KEYWORD_BACKLOG_REVIEW | L59: HIGH
A60: 57 | B60: 日本 | C60: 2023-08-09 | D60: KISHIDA Fumio | E60: HEAD | F60: SPEECH | G60: Video Message by Prime Minister KISHIDA Fumio at the Nagasaki Peace Memorial Ceremony | H60: https://japan.kantei.go.jp/101_kishida/statement/202308/09message.html | J60: 2026-09-22 | K60: KANTEI_ARCHIVE_KEYWORD_BACKLOG_REVIEW | L60: HIGH
A61: 58 | B61: 日本 | C61: 2023-08-15 | D61: KISHIDA Fumio | E61: HEAD | F61: SPEECH | G61: Address by Prime Minister Kishida at the Seventy-Eighth National Memorial Ceremony for the War Dead (Speeches and Statements <br>by the Prime Minister) | Prime Minister's Office of Japan | H61: https://japan.kantei.go.jp/101_kishida/statement/202308/15shikiji.html | J61: NA | K61: (直接クロール、パイプライン01-09段階) | L61: MEDIUM
A62: 59 | B62: 日本 | C62: 2024-06-23 | D62: KISHIDA Fumio | E62: HEAD | F62: SPEECH | G62: Address by Prime Minister Kishida for the Memorial Ceremony to Commemorate the Fallen on the 79th Anniversary of the End of the Battle of Okinawa | H62: https://japan.kantei.go.jp/101_kishida/statement/202406/23okinawa.html | J62: 2026-09-22 | K62: MANUAL_REVIEW_BACKLOG | L62: HIGH
A63: 60 | B63: 日本 | C63: 2024-07-27 | D63: KISHIDA Fumio | E63: HEAD | F63: STATEMENT | G63: Message by Prime Minister KISHIDA Fumio on the Inscription of “Sado Island Gold Mines” on UNESCO's World Heritage List | H63: https://japan.kantei.go.jp/101_kishida/statement/202407/27sado.html | J63: 2026-09-22 | K63: KANTEI_ARCHIVE_KEYWORD_BACKLOG_REVIEW | L63: MEDIUM
A64: 61 | B64: 日本 | C64: 2024-07-27 | D64: KAMIKAWA Yoko | E64: MINISTER | F64: STATEMENT | G64: The inscription of “Sado Island Gold Mines” on the World Heritage List (Statement by Foreign Minister KAMIKAWA Yoko) | H64: https://www.mofa.go.jp/press/release/pressite_000001_00453.html | I64: https://web.archive.org/web/20240727181324id_/https://www.mofa.go.jp/press/release/pressite_000001_00453.html | J64: 2026-09-22 | K64: MOFA_JAPAN_WAYBACK_MACHINE_FETCH | L64: HIGH
A65: 62 | B65: 日本 | C65: 2024-08-06 | D65: KISHIDA Fumio | E65: HEAD | F65: SPEECH | G65: Address by Prime Minister KISHIDA Fumio at the Hiroshima Peace Memorial Ceremony | H65: https://japan.kantei.go.jp/101_kishida/statement/202408/06hiroshima.html | J65: 2026-09-22 | K65: KANTEI_ARCHIVE_KEYWORD_BACKLOG_REVIEW | L65: HIGH
A66: 63 | B66: 日本 | C66: 2024-08-09 | D66: KISHIDA Fumio | E66: HEAD | F66: SPEECH | G66: Address by Prime Minister KISHIDA Fumio at the Nagasaki Peace Memorial Ceremony | H66: https://japan.kantei.go.jp/101_kishida/statement/202408/09nagasaki.html | J66: 2026-09-22 | K66: KANTEI_ARCHIVE_KEYWORD_BACKLOG_REVIEW | L66: HIGH
A67: 64 | B67: 日本 | C67: 2024-08-15 | D67: KISHIDA Fumio | E67: HEAD | F67: SPEECH | G67: Address by Prime Minister Kishida at the Seventy-Ninth National Memorial Ceremony for the War Dead (Speeches and Statements <br>by the Prime Minister) | Prime Minister's Office of Japan | H67: https://japan.kantei.go.jp/101_kishida/statement/202408/15shikiji.html | J67: NA | K67: (直接クロール、パイプライン01-09段階) | L67: MEDIUM
A68: 65 | B68: 日本 | C68: 2025-03-29 | D68: ISHIBA Shigeru | E68: HEAD | F68: SPEECH | G68: Address by Prime Minister ISHIBA Shigeru to the Japan-U.S. Iwo-To Reunion of Honor Ceremony | H68: https://japan.kantei.go.jp/103/statement/202503/29tsuitounokotoba.html | J68: 2026-09-22 | K68: MANUAL_REVIEW_BACKLOG | L68: HIGH
A69: 66 | B69: 日本 | C69: 2025-06-09 | D69: ISHIBA Shigeru | E69: HEAD | F69: PRESS_CONFERENCE | G69: Press Conference by Prime Minister ISHIBA Shigeru Regarding His Summit Telephone Talk with President Lee of the Republic of Korea and Other Matters | H69: https://japan.kantei.go.jp/103/statement/202506/09kaiken.html | J69: 2026-09-22 | K69: MANUAL_REVIEW_BACKLOG | L69: MEDIUM
A70: 67 | B70: 日本 | C70: 2025-06-23 | D70: ISHIBA Shigeru | E70: HEAD | F70: PRESS_CONFERENCE | G70: Press Conference by Prime Minister ISHIBA Shigeru regarding the Memorial Ceremony to Commemorate the Fallen on the 80th Anniversary of the End of the Battle of Okinawa and Other Matters | H70: https://japan.kantei.go.jp/103/statement/202506/23kaiken.html | J70: 2026-09-22 | K70: MANUAL_REVIEW_BACKLOG | L70: HIGH
A71: 68 | B71: 日本 | C71: 2025-06-23 | D71: ISHIBA Shigeru | E71: HEAD | F71: SPEECH | G71: Address by Prime Minister Ishiba for the Memorial Ceremony to Commemorate the Fallen on the 80th Anniversary of the End of the Battle of Okinawa | H71: https://japan.kantei.go.jp/103/statement/202506/23okinawa.html | J71: 2026-09-22 | K71: MANUAL_REVIEW_BACKLOG | L71: HIGH
A72: 69 | B72: 日本 | C72: 2025-08-06 | D72: ISHIBA Shigeru | E72: HEAD | F72: SPEECH | G72: Address by Prime Minister ISHIBA Shigeru at the Hiroshima Peace Memorial Ceremony | H72: https://japan.kantei.go.jp/103/statement/202508/06hiroshima.html | J72: 2026-09-22 | K72: KANTEI_ARCHIVE_KEYWORD_BACKLOG_REVIEW | L72: HIGH
A73: 70 | B73: 日本 | C73: 2025-08-09 | D73: ISHIBA Shigeru | E73: HEAD | F73: SPEECH | G73: Address by Prime Minister ISHIBA Shigeru at the Nagasaki Peace Memorial Ceremony | H73: https://japan.kantei.go.jp/103/statement/202508/09nagasaki.html | J73: 2026-09-22 | K73: KANTEI_ARCHIVE_KEYWORD_BACKLOG_REVIEW | L73: HIGH
A74: 71 | B74: 日本 | C74: 2025-08-15 | D74: ISHIBA Shigeru | E74: HEAD | F74: PRESS_CONFERENCE | G74: Press Conference by Prime Minister ISHIBA Shigeru regarding the Address He Delivered at the National Memorial Ceremony for the War Dead and Other Matters (Speeches and Statements <br>by the Prime Minister) | Prime Minister's Office of Japan | H74: https://japan.kantei.go.jp/103/statement/202508/15kaiken.html | J74: NA | K74: (直接クロール、パイプライン01-09段階) | L74: HIGH
A75: 72 | B75: 日本 | C75: 2025-08-15 | D75: ISHIBA Shigeru | E75: HEAD | F75: SPEECH | G75: Address by Prime Minister Ishiba at the Eightieth National Memorial Ceremony for the War Dead (Speeches and Statements <br>by the Prime Minister) | Prime Minister's Office of Japan | H75: https://japan.kantei.go.jp/103/statement/202508/15shikiji.html | J75: NA | K75: (直接クロール、パイプライン01-09段階) | L75: MEDIUM
A76: 73 | B76: 韓国 | C76: 2020-08-14 | D76: Moon Jae-in | E76: HEAD | F76: PRESS_CONFERENCE | G76: Message from President Moon Jae-in on National Day to Honor Japanese Military Comfort Women Victims | H76: http://webarchives.pa.go.kr/19th/english.president.go.kr/BriefingSpeeches/Others/979 | J76: NA | K76: (直接クロール、パイプライン01-09段階) | L76: HIGH
... A82: 79 | B82: 韓国 | C82: 2022-08-15 | D82: Yoon Suk Yeol | E82: HEAD | F82: SPEECH | G82: Address by President Yoon Suk Yeol on Korea's 77th Liberation Day | Speeches and Remarks > Speeches and Remarks | H82: http://webarchives.pa.go.kr/20th/eng.president.go.kr/speeches/k4bSEz3J | J82: NA | K82: (直接クロール、パイプライン01-09段階) | L82: MEDIUM
A83: 80 | B83: 韓国 | C83: 2023-03-01 | D83: Yoon Suk Yeol | E83: HEAD | F83: SPEECH | G83: Address by President Yoon Suk Yeol on 104th March First Independence Movement Day | H83: https://eng.president.go.kr/speeches/lpuJ3C1r | I83: https://web.archive.org/web/20230307135439id_/https://eng.president.go.kr/speeches/lpuJ3C1r | J83: 2026-09-22 | K83: WAYBACK_CDX_KOREA_PRESIDENTIAL_SPEECHES | L83: HIGH
A84: 81 | B84: 韓国 | C84: 2023-03-17 | D84: Yoon Suk Yeol | E84: HEAD | F84: OTHER | G84: President Yoon hails "new start" in ties with Japan, attends dinner | H84: https://eng.president.go.kr/briefing/Le8znpcj | I84: https://web.archive.org/web/20241102225157id_/https://eng.president.go.kr/briefing/Le8znpcj | J84: 2026-09-22 | K84: WAYBACK_CDX_KOREA_PRESIDENTIAL_BRIEFING | L84: HIGH
A85: 82 | B85: 韓国 | C85: 2023-03-22 | D85: Yoon Suk Yeol | E85: HEAD | F85: SPEECH | G85: President Yoon urges 'future-oriented ties' with Japan in televised speech | H85: https://eng.president.go.kr/briefing/s78dvSmB | I85: https://web.archive.org/web/20230606160232id_/https://eng.president.go.kr/briefing/s78dvSmB | J85: 2026-09-22 | K85: WAYBACK_CDX_KOREA_PRESIDENTIAL_BRIEFING | L85: HIGH
A86: 83 | B86: 韓国 | C86: 2023-03-28 | D86: MOFA Spokesperson | E86: OFFICIAL | F86: STATEMENT | G86: MOFA Spokesperson's Statement on Japan's Authorization of Elementary School Textbooks | H86: https://www.mofa.go.kr/eng/brd/m_5676/view.do?seq=322177 | J86: 2026-09-22 | K86: MOFA_KOREA_DIRECT_FETCH | L86: HIGH
A87: 84 | B87: 韓国 | C87: 2023-05-08 | D87: Office of the President, Republic of Korea (news release) | E87: OFFICIAL | F87: OTHER | G87: President Yoon hosts dinner for Japan's PM at the official residence | H87: https://eng.president.go.kr/briefing/qEY1X9Aw | I87: https://web.archive.org/web/20230509115516id_/https://eng.president.go.kr/briefing/qEY1X9Aw | J87: 2026-09-22 | K87: WAYBACK_CDX_KOREA_PRESIDENTIAL_BRIEFING | L87: MEDIUM
A88: 85 | B88: 韓国 | C88: 2023-05-08 | D88: Yoon Suk Yeol | E88: HEAD | F88: SPEECH | G88: Remarks by President Yoon Suk Yeol in Lecture for Keio University Students | H88: https://eng.president.go.kr/speeches/C3nefmgN | I88: https://web.archive.org/web/20231017221927id_/https://eng.president.go.kr/speeches/C3nefmgN | J88: 2026-09-22 | K88: WAYBACK_CDX_KOREA_PRESIDENTIAL_SPEECHES | L88: MEDIUM
A89: 86 | B89: 韓国 | C89: 2023-08-15 | D89: Yoon Suk Yeol | E89: HEAD | F89: SPEECH | G89: Address by President Yoon Suk Yeol on Korea's 78th Liberation Day | Speeches and Remarks > Speeches and Remarks | H89: http://webarchives.pa.go.kr/20th/eng.president.go.kr/speeches/ChFr4MEm | J89: NA | K89: (直接クロール、パイプライン01-09段階) | L89: MEDIUM
A90: 87 | B90: 韓国 | C90: 2024-01-31 | D90: MOFA Spokesperson | E90: OFFICIAL | F90: STATEMENT | G90: MOFA Spokesperson's Statement on Japanese Foreign Minister's Remarks regarding Dokdo and Sado Island Gold Mines in Foreign Policy Speech | H90: https://www.mofa.go.kr/eng/brd/m_5676/view.do?seq=322402 | J90: 2026-09-22 | K90: MOFA_KOREA_DIRECT_FETCH_WEB_SEARCH | L90: HIGH
A91: 88 | B91: 韓国 | C91: 2024-03-01 | D91: Yoon Suk Yeol | E91: HEAD | F91: SPEECH | G91: Address by President Yoon Suk Yeol on the 105th March First Independence Movement Day | H91: https://eng.president.go.kr/speeches/x9M5tP3s | I91: https://web.archive.org/web/20240301083914id_/https://eng.president.go.kr/speeches/x9M5tP3s | J91: 2026-09-22 | K91: WAYBACK_CDX_KOREA_PRESIDENTIAL_SPEECHES | L91: HIGH
A92: 89 | B92: 韓国 | C92: 2024-04-19 | D92: MOFA Spokesperson | E92: OFFICIAL | F92: STATEMENT | G92: MOFA Spokesperson's Statement on Japan's Authorization of a Middle School Textbook | H92: https://www.mofa.go.kr/eng/brd/m_5676/view.do?seq=322527 | J92: 2026-09-22 | K92: MOFA_KOREA_DIRECT_FETCH | L92: HIGH
A93: 90 | B93: 韓国 | C93: 2024-08-15 | D93: Yoon Suk Yeol | E93: HEAD | F93: SPEECH | G93: Address by President Yoon Suk Yeol on the 79th Liberation Day | Speeches and Remarks > Speeches and Remarks | H93: http://webarchives.pa.go.kr/20th/eng.president.go.kr/speeches/YhZsGrfN | J93: NA | K93: (直接クロール、パイプライン01-09段階) | L93: MEDIUM
A94: 91 | B94: 韓国 | C94: 2025-03-27 | D94: MOFA Spokesperson | E94: OFFICIAL | F94: STATEMENT | G94: MOFA Spokesperson's Statement on Japan's Authorization of High School Textbooks (March 25, 2025) | H94: https://www.mofa.go.kr/eng/brd/m_5674/view.do?seq=321114 | J94: 2026-09-22 | K94: MOFA_KOREA_DIRECT_FETCH | L94: HIGH
A95: 92 | B95: 韓国 | C95: 2025-08-14 | D95: Lee Jae Myung | E95: HEAD | F95: STATEMENT | G95: President Lee's message on National Memorial Day for Japanese Military Comfort Women Victims (2025) | H95: https://www.aa.com.tr/en/asia-pacific/comfort-women-issue-remains-unresolved-says-south-koreas-president-lee-ahead-of-maiden-visit-to-japan/3659615 | J95: 2026-09-22 | K95: WEB_SEARCH_NEWS_QUOTE | L95: MEDIUM
A96: 93 | B96: 韓国 | C96: 2025-08-15 | D96: Lee Jae Myung | E96: HEAD | F96: SPEECH | G96: Address by President Lee Jae Myung on Korea's 80th Liberation Day | H96: https://en.president.go.kr/president/statements-remarks/96ecUYVL | J96: 2026-09-22 | K96: AJAX_ARCHIVE_CRAWL | L96: HIGH
A97: 94 | B97: 韓国 | C97: 2025-08-15 | D97: MOFA Spokesperson | E97: OFFICIAL | F97: STATEMENT | G97: MOFA Spokesperson's Commentary on Sending Offerings to and Paying Respects at Yasukuni Shrine | H97: https://www.mofa.go.kr/eng/brd/m_5676/view.do?seq=322933 | J97: 2026-09-22 | K97: MOFA_KOREA_DIRECT_FETCH | L97: HIGH
A98: 95 | B98: 韓国 | C98: 2025-08-21 | D98: Lee Jae Myung | E98: HEAD | F98: WRITTEN_RESPONSE | G98: 'We should not nix accords with Japan on comfort women, forced work' (Yomiuri Shimbun interview, reported via korea.net) | H98: https://www.korea.net/NewsFocus/policies/view?articleId=277613 | J98: 2026-09-22 | K98: KOREA_NET_OFFICIAL_PORTAL_WEB_SEARCH | L98: HIGH
A99: 96 | B99: 韓国 | C99: 2025-08-23 | D99: Lee Jae Myung | E99: HEAD | F99: PRESS_CONFERENCE | G99: Lee, Ishiba vow future-oriented ties in 1st joint statement in 17 years (Korea Herald report) | H99: https://www.koreaherald.com/article/10560185 | J99: 2026-09-22 | K99: WEB_SEARCH_NEWS_QUOTE | L99: MEDIUM
A100: 97 | B100: 韓国 | C100: 2026-03-24 | D100: MOFA Spokesperson | E100: OFFICIAL | F100: STATEMENT | G100: MOFA Spokesperson's Statement on Japan's Authorization of High School Textbooks (March 24, 2026) | H100: https://www.mofa.go.kr/eng/brd/m_5676/view.do?seq=323224 | J100: 2026-09-22 | K100: MOFA_KOREA_DIRECT_FETCH | L100: HIGH
A101: 98 | B101: 韓国 | C101: 2026-04-21 | D101: MOFA Spokesperson | E101: OFFICIAL | F101: STATEMENT | G101: S. Korea expresses regret over Japanese PM's offering to war-linked shrine (Xinhua report of MOFA statement) | H101: https://english.news.cn/20260421/0df8aec190ed4efb837e5a932aa25f21/c.html | J101: 2026-09-22 | K101: WIRE_SERVICE_QUOTE_WEB_SEARCH | L101: MEDIUM
A102: 99 | B102: 韓国 | C102: 2026-05-19 | D102: Lee Jae Myung | E102: HEAD | F102: JOINT_STATEMENT | G102: Joint Press Statement by President Lee Jae Myung on the occasion of the Korea-Japan Summit | H102: https://en.president.go.kr/president/statements-remarks/VWkmhWnq | J102: 2026-09-22 | K102: AJAX_ARCHIVE_CRAWL | L102: MEDIUM
A103: 100 | B103: 韓国 | C103: 2026-07-15 | D103: MOFA Official (unnamed, background briefing) | E103: OFFICIAL | F103: OTHER | G103: Seoul says UNESCO draft finds Japan's Sado mine measures still insufficient | H103: https://www.koreaherald.com/article/10810212 | J103: 2026-09-22 | K103: WEB_SEARCH_NEWS_QUOTE | L103: MEDIUM
... A105: 102 | B105: 韓国 | C105: 2026-08-15 | D105: Lee Jae Myung | E105: HEAD | F105: SPEECH | G105: Address by President Lee Jae Myung on Korea's 81st Liberation Day | H105: https://en.president.go.kr/president/statements-remarks/MK8xT9SG | J105: 2026-09-22 | K105: AJAX_ARCHIVE_CRAWL | L105: HIGH

Sheet MainAxis_101
A1: record_id | B1: country | C1: date | D1: year | E1: speaker_name | F1: speaker_position | G1: speaker_level | H1: institution | I1: document_type | J1: document_title | K1: question_text | L1: response_text | M1: relevant_excerpt | N1: issue_primary | O1: issue_secondary | P1: kingdon_problem | Q1: kingdon_policy | R1: kingdon_politics | S1: kingdon_confidence | T1: apology | U1: explanation | V1: remorse | W1: reflection | X1: remedy | Y1: pardon_or_forgiveness | Z1: responsibility_actor | AA1: agency_explicit | AB1: audience_orientation | AC1: source_language | AD1: official_translation | AE1: source_url | AF1: retrieval_date | AG1: archive_url | AH1: collection_method | AI1: coder_notes | AJ1: classification_confidence | AK1: duplicate_group_id | AL1: canonical_record
A2: 37339e32-cd17-43ae-bc8b-654c9b92a7b0 | B2: japan | C2: 2022-08-15 | D2: 2022 | E2: KISHIDA Fumio | F2: Prime Minister of Japan | G2: HEAD | H2: Prime Minister's Office of Japan (Kantei) | I2: SPEECH | J2: Address by Prime Minister Kishida at the Seventy-Seventh National Memorial Ceremony for the War Dead (Speeches and Statements <br>by the Prime Minister) | Prime Minister's Office of Japan | L2: Address by Prime Minister Kishida at the Seventy-Seventh National Memorial Ceremony for the War Dead (Speeches and Statements <br>by the Prime Minister) | Prime Minister's Office of Japan Address by Prime Minister Kishida at the Seventy-Seventh National Memorial Ceremony for the War Dead August 15, 2022 Tweet [Provisional translation] In the gracious presence of Their Majesties the Emperor and Empress, and with the attendance of bereaved families of the war dead, distinguished representatives of all sectors of society, and many others, I hereby commence the annual National Memorial Ceremony for the War Dead. More than three million of our compatriots lost their lives during the war. Some fell on the battlefields worrying about the future of their homeland and wishing for the happiness of their families. Others perished in remote foreign countries after the war. And many fell victim to the violent turmoil of war in the atomic bombings of Hiroshima and Nagasaki, the air raids on numerous cities, and the ground battles in Okinawa, among others. Here, before the souls of all who lost their lives, I offer my heartfelt prayers for their repose. We will not forget, even for a moment, that the peace and prosperity we enjoy today was built atop the precious lives and the history of suffering of the war dead. I express my deepest respect and gratitude once more. Never will we forget the large number of war dead whose remains have still not been recovered. Taking it as the responsibility of the nation, we shall spare no effort to enable their remains to return to their hometowns at the earliest possible time. Since the end of the war, Japan has consistently walked the path of a peace-loving nation. Taking the lessons of history deeply into our hearts, we have made all possible efforts for world peace and prosperity. We must never again repeat the devastation of war. We will continue to remain committed to this resolute pledge. In this world in which conflicts have not yet ceased, under the banner of "Proactive Contribution to Peace," Japan is determined to join forces with the international community and do its utmost to resolve the various challenges facing the world. We shall carve out the future of our nation for the sake of the generation alive now and the generations of tomorrow. I will conclude my address by once again offering my heartfelt prayers for the repose of the souls of the war dead and for the happiness of the members of their bereaved families. KISHIDA Fumio Prime Minister of Japan August 15, 2022 More Related Link Japanese Tweet Archives (Archived entries for the 101st through 103rd Prime Ministers) The 103rd Prime Minister ISHIBA Shigeru Open Close 2025 2024 The 102nd Prime Minister ISHIBA Shigeru Open Close 2024 The 101st Prime Minister KISHIDA Fumio Open Close 2024 2023 2022 2021 Tag List View All Return to the Speeches and Statements by the Prime Minister | M2: Address by Prime Minister Kishida at the Seventy-Seventh National Memorial Ceremony for the War Dead (Speeches and Statements <br>by the Prime Minister) | Prime Minister's Office of Japan Address by Prime Minister Kishida at the Seventy-Seventh National Memorial Ceremony for the War Dead August 15, 2022 Tweet [Provisional translation] In the gracious presence of Their Majesties the Emperor and Empress, and with the attendance of bereaved families of the war dead, distinguished representatives of all sectors of society, and many others, I hereby commence the annual National Memorial Ceremony for the War Dead. More than three million of our compatriots lost their lives during the war. Some fell on the battlefields worrying about the future of their homeland and wishing for the happiness of their families. Others perished in remote foreign countries after the war. And many fell victim to the violent turmoil of war in the atomic bombings of Hiroshima and Nagasaki, the air raids on numerous cities, and the ground battles in Okinawa, among others. Here, before the souls of all who lost their lives, I offer my heartfelt prayers for their repose. We will not forget, even for a moment, that the peace and prosperity we enjoy today was built atop the precious lives and the history of suffering of the war dead. I express my deepest respect and gratitude once more. Never will we forget the large number of war dead whose remains have still not been recovered. Taking it as the responsibility of the nation, we shall spare no effort to enable their remains to return to their hometowns at the earliest possible time. Since the end of the war, Japan has consistently walked the path of a peace-loving nation. Taking the lessons of history deeply into our hearts, we have made all possible efforts for world peace and prosperity. We must never again repeat the devastation of war. We will continue to remain committed to this resolute pledge. In this world in which conflicts have not yet ceased, under the banner of "Proactive Contribution to Peace," Japan is determined to join forces with the international community and do its utmost to resolve the various challenges facing the world. We shall carve out the future of our nation for the sake of the generation alive now and the generations of tomorrow. I will conclude my address by once again offering my heartfelt prayers for the repose of the souls of the war dead and for the happiness of the members of their bereaved families. KISHIDA Fumio Prime Minister of Japan August 15, 2022 More Related Link Japanese Tweet Archives (Archived entries for the 101st through 103rd Prime Ministers) The 103rd Prime Minister ISHIBA Shigeru Open Close 2025 2024 The 102nd Prime Minister ISHIBA Shigeru Open Close 2024 The 101st Prime Minister KISHIDA Fumio Open Close 2024 2023 2022 2021 Tag List View All Return to the Speeches and Statements by the Prime Minister | N2: WAR_GENERAL | O2: NA | P2: 0 | Q2: 1 | R2: 0 | S2: MEDIUM | T2: 0 | U2: 0 | V2: 0 | W2: 1 | X2: 1 | Y2: 0 | Z2: UNSPECIFIED | AA2: 0 | AB2: DOMESTIC | AC2: en | AD2: 1 | AE2: https://japan.kantei.go.jp/101_kishida/statement/202208/_00006.html | AF2: NA | AG2: NA | AH2: NA | AI2: 77th National Memorial Ceremony for the War Dead (Kishida's first). Adds "taking the lessons of history deeply into our hearts" but still no apology/remorse toward foreign victims. | AJ2: MEDIUM | AK2: 6d37ea79-403b-52b7-a520-3f8875766af8 | AL2: 1
A3: e7c2f241-4e6c-44d2-8461-4db00c0314ab | B3: japan | C3: 2023-03-06 | D3: 2023 | E3: KISHIDA Fumio | F3: Prime Minister of Japan | G3: HEAD | H3: Prime Minister's Office of Japan (Kantei) | I3: PRESS_CONFERENCE | J3: Press Conference by the Prime Minister regarding the Issue of Former Civilian Workers from the Korean Peninsula (Speeches and Statements <br>by the Prime Minister) | Prime Minister's Office of Japan | L3: Press Conference by the Prime Minister regarding the Issue of Former Civilian Workers from the Korean Peninsula (Speeches and Statements <br>by the Prime Minister) | Prime Minister's Office of Japan #DiplomacySecurity Press Conference by the Prime Minister regarding the Issue of Former Civilian Workers from the Korean Peninsula March 6, 2023 Tweet [Provisional translation] [Provisional translation] (On the Government’s reaction to the issue of former civilian workers from the Korean Peninsula, the Japan-ROK Summit Meeting and his historic recognition of the Japan-ROK relations) Earlier today, the Government of the Republic of Korea (ROK) announced their measures regarding the issue of former civilian workers from the Korean Peninsula. We regard the latest measures announced by the Government of ROK as a step towards restoring healthy Japan-ROK relations. ROK President Yoon Suk Yeol and I have been in communication on various occasions, including our meeting in New York and the Japan-ROK Summit Meeting in Cambodia. I believe that Japan and the ROK are important neighboring countries in addressing various issues in the international community, and in light of the current international situation and strategic environment, we recognize the importance of Japan-ROK and Japan-U.S.-ROK cooperation, as well as the importance of cooperation with the ROK in working toward a Free and Open Indo-Pacific. We intend to closely communicate with President Yoon down the road. Regarding the question about a future Japan-ROK Summit Meeting, we have not yet decided on any specific diplomatic schedule in Japan-ROK relations. We have taken over the position of previous cabinets on the recognition of the history, including the Japan-ROK Joint Declaration announced in October 1998. This is the position that the Government of Japan takes. (On his thoughts on ensuring the irreversibility) We regard the measures announced today by the Government of ROK as a step towards restoring healthy Japan-ROK relations. We understand that the Government of ROK has also made various efforts on its part. We have high hopes that this could be an opportunity to strengthen and strongly advance Japan-ROK relations while implementing the measures. To this end, I would like to emphasize the importance of communicating closely with President Yoon. (On whether the concerns over possible reversal on the irreversibility has been eliminated) I would like to refrain from going into a hypothetical question. We appreciate the announced measures and hope that Japan-ROK relations will move forward. To that end, we will continue to communicate with each other. (On the Japan-ROK Export Control Policy Dialogue) Let me first clarify that the "update of licensing policies and procedures on exports of controlled items to the ROK" has been conducted to ensure proper implementation of export control from a security perspective and therefore is a separate issue from the issue of former civilian workers from the Korean Peninsula. And today, I have been informed that in order to restore the pre-July 2019 status quo regarding the pending issue of export control, both sides have decided to promptly hold related bilateral consultations between the Japanese and ROK authorities, in light of the ROK's announcement of its decision to suspend its WTO dispute settlement procedures. I hope that the consultations will proceed steadily. For further details, the Ministry of Economy, Trade and Industry is ready to answer your questions. More Related Link Japanese Tweet Archives (Archived entries for the 101st through 103rd Prime Ministers) The 103rd Prime Minister ISHIBA Shigeru Open Close 2025 2024 The 102nd Prime Minister ISHIBA Shigeru Open Close 2024 The 101st Prime Minister KISHIDA Fumio Open Close 2024 2023 2022 2021 Tag List View All Related Pages Return to the Speeches and Statements by the Prime Minister | M3: Press Conference by the Prime Minister regarding the Issue of Former Civilian Workers from the Korean Peninsula (Speeches and Statements <br>by the Prime Minister) | Prime Minister's Office of Japan #DiplomacySecurity Press Conference by the Prime Minister regarding the Issue of Former Civilian Workers from the Korean Peninsula March 6, 2023 Tweet [Provisional translation] [Provisional translation] (On the Government’s reaction to the issue of former civilian workers from the Korean Peninsula, the Japan-ROK Summit Meeting and his historic recognition of the Japan-ROK relations) Earlier today, the Government of the Republic of Korea (ROK) announced their measures regarding the issue of former civilian workers from the Korean Peninsula. We regard the latest measures announced by the Government of ROK as a step towards restoring healthy Japan-ROK relations. ROK President Yoon Suk Yeol and I have been in communication on various occasions, including our meeting in New York and the Japan-ROK Summit Meeting in Cambodia. I believe that Japan and the ROK are important neighboring countries in addressing various issues in the international community, and in light of the current international situation and strategic environment, we recognize the importance of Japan-ROK and Japan-U.S.-ROK cooperation, as well as the importance of cooperation with the ROK in working toward a Free and Open Indo-Pacific. We intend to closely communicate with President Yoon down the road. Regarding the question about a future Japan-ROK Summit Meeting, we have not yet decided on any specific diplomatic schedule in Japan-ROK relations. We have taken over the position of previous cabinets on the recognition of the history, including the Japan-ROK Joint Declaration announced in October 1998. This is the position that the Government of Japan takes. (On his thoughts on ensuring the irreversibility) We regard the measures announced today by the Government of ROK as a step towards restoring healthy Japan-ROK relations. We understand that the Government of ROK has also made various efforts on its part. We have high hopes that this could be an opportunity to strengthen and strongly advance Japan-ROK relations while implementing the measures. To this end, I would like to emphasize the importance of communicating closely with President Yoon. (On whether the concerns over possible reversal on the irreversibility has been eliminated) I would like to refrain from going into a hypothetical question. We appreciate the announced measures and hope that Japan-ROK relations will move forward. To that end, we will continue to communicate with each other. (On the Japan-ROK Export Control Policy Dialogue) Let me first clarify that the "update of licensing policies and procedures on exports of controlled items to the ROK" has been conducted to ensure proper implementation of export control from a security perspective and therefore is a separate issue from the issue of former civilian workers from the Korean Peninsula. | N3: FORCED_LABOR | O3: COMPENSATION_REPARATION;HISTORICAL_RECOGNITION_GENERAL | P3: 1 | Q3: 1 | R3: 1 | S3: HIGH | T3: 0 | U3: 1 | V3: 0 | W3: 0 | X3: 1 | Y3: 0 | Z3: UNSPECIFIED | AA3: 0 | AB3: MIXED | AC3: en | AD3: 1 | AE3: https://japan.kantei.go.jp/101_kishida/statement/202303/_00004.html | AF3: NA | AG3: NA | AH3: NA | AI3: Kishida's reaction to the ROK government's March 2023 third-party reimbursement plan for wartime forced-labor court judgments against Japanese firms. Cites the Oct 1998 Japan-ROK Joint Declaration (Obuchi-Kim) as the standing "recognition of history" position by reference only, without re-quoting its apology/remorse language. remedy=1 refers to the ROK's own compensation measure, which Japan welcomes, not a new Japanese remedy. | AJ3: HIGH | AK3: fcb0a3eb-0570-5882-8283-33e807cdb232 | AL3: 1
A4: da272986-2674-4610-864b-a25a61e8e58e | B4: japan | C4: 2023-03-16 | D4: 2023 | E4: KISHIDA Fumio | F4: Prime Minister of Japan | G4: HEAD | H4: Prime Minister's Office of Japan (Kantei) | I4: PRESS_CONFERENCE | J4: Joint Press Conference by the Leaders of Japan and the Republic of Korea (Speeches and Statements <br>by the Prime Minister) | Prime Minister's Office of Japan | L4: Joint Press Conference by the Leaders of Japan and the Republic of Korea (Speeches and Statements <br>by the Prime Minister) | Prime Minister's Office of Japan #DiplomacySecurity #JPNKORsummit #FreeOpenIndoPacific #AbductionsByNK #NKmissile Joint Press Conference by the Leaders of Japan and the Republic of Korea March 16, 2023 Tweet [Provisional translation] [Opening Statement by Prime Minister KISHIDA Fumio] I welcome President YOON Suk Yeol of the Republic of Korea (ROK) most wholeheartedly in his visit to Japan. This week, in Tokyo the cherry blossoms have come into full bloom, and now, as we emerge from a long period of winter, we welcome the President of the ROK to Japan as the first bilateral visit in roughly 12 years. In my meeting with President Yoon, we were in full agreement that the strengthening of Japan-ROK relations is a matter of pressing urgency in the current strategic environment, and that we will further develop Japan-ROK relations, based on the foundation of the friendly and cooperative relations we have cultivated since the normalization of our diplomatic relations in 1965. Recently, the ROK Government announced measures regarding the issue of former civilian workers from the Korean Peninsula. The Government of Japan commends these measures as a step towards restoring healthy Japan-ROK relations, which have been in extremely severe circumstances. During our summit meeting, we confirmed that the Government of Japan takes up in its entirety the position of previous cabinets on the recognition of the history, including the Japan-ROK Joint Declaration announced in October 1998. I look forward to a robust expansion of exchanges between our two countries in the future in such fields as politics, the economy, and culture, alongside the implementation of these measures. In order to open up a new chapter in Japan-ROK relations, during the meeting I held with President Yoon today, we agreed to restart "shuttle diplomacy," with the leaders of our nations each frequently visiting the other's country, regardless of the form in which those visits take place. In addition, with regard to Japan-ROK relations, we agreed to invigorate communications between our governments across a wide range of fields. In concrete terms, first of all, we shared the same stance that we will restart at an early time the Japan-ROK Security Dialogue and also the Japan-ROK Vice-Ministerial Strategic Dialogue, both of which have been suspended for a long time, and we agreed on the importance of relaunching the high-level Japan-ROK-China trilateral process at an early time. We also decided to launch consultations between Japan and the ROK regarding economic security. In addition, we made progress in the area of export control. In the future we will promote a wide range of dialogue in various policy areas between our respective ministries and agencies in charge. In addition, private sector exchanges and cooperation are a framework supporting bilateral relations. I welcome the fact that, taking the opportunity of President Yoon's visit to Japan, economic federations in both Japan and the ROK have announced they will each establish a fund for future-oriented Japan-ROK cooperation and exchange. The Government of Japan will continue to support exchanges among young people, who will hold the key to our nations' futures. Exchanges between our two countries have now recovered, and as for the number of foreign visitors to our two countries, it is ROK and Japanese nationals that are each visiting the other's country in the greatest number. I very much look forward to a further acceleration of the virtuous cycle of increasingly active people-to-people exchanges and improvements in our relations. President Yoon and I also shared a common recognition of the current harsh security environment. In particular, with regard to responses to North Korea, which is further pursuing nuclear and missile activities, including this morning's launch of an ICBM-class ballistic missile, we confirmed the importance of further reinforcing the deterrence and response capabilities of the Japan-U.S. Alliance and ROK-U.S. Alliance and of vigorously promoting security cooperation both between Japan and the ROK and among Japan, the ROK, and the U.S. The window for dialogue with North Korea remains open. That fact has not changed. President Yoon also expressed strong support once again regarding the abductions issue. Moreover, we reaffirmed the importance of bringing about a free and open Indo-Pacific at this historic turning point, and we shared a common recognition of the importance of like-minded countries working together to fully defend the free and open international order based on the rule of law. This visit by President Yoon to Japan has been a major step forward for the normalization of Japan-ROK relations. I am looking forward to the opportunity to speak in even greater depth with President Yoon and the First Lady at the dinner scheduled to take place after this. With President Yoon's visit to Japan as a turning point, I have high hopes for us to cultivate our trust and friendship and for Japan-ROK relations to make great strides forward. More Related Link Photos (PM in Action) Summary Japanese Tweet Archives (Archived entries for the 101st through 103rd Prime Ministers) The 103rd Prime Minister ISHIBA Shigeru Open Close 2025 2024 The 102nd Prime Minister ISHIBA Shigeru Open Close 2024 The 101st Prime Minister KISHIDA Fumio Open Close 2024 2023 2022 2021 Tag List View All Related Pages Return to the Speeches and Statements by the Prime Minister | M4: In my meeting with President Yoon, we were in full agreement that the strengthening of Japan-ROK relations is a matter of pressing urgency in the current strategic environment, and that we will further develop Japan-ROK relations, based on the foundation of the friendly and cooperative relations we have cultivated since the normalization of our diplomatic relations in 1965. Recently, the ROK Government announced measures regarding the issue of former civilian workers from the Korean Peninsula. The Government of Japan commends these measures as a step towards restoring healthy Japan-ROK relations, which have been in extremely severe circumstances. During our summit meeting, we confirmed that the Government of Japan takes up in its entirety the position of previous cabinets on the recognition of the history, including the Japan-ROK Joint Declaration announced in October 1998. I look forward to a robust expansion of exchanges between our two countries in the future in such fields as politics, the economy, and culture, alongside the implementation of these measures. In order to open up a new chapter in Japan-ROK relations, during the meeting I held with President Yoon today, we agreed to restart "shuttle diplomacy," with the leaders of our nations each frequently visiting the other's country, regardless of the form in which those visits take place. In addition, with regard to Japan-ROK relations, we agreed to invigorate communications between our governments across a wide range of fields. In the future we will promote a wide range of dialogue in various policy areas between our respective ministries and agencies in charge. In addition, private sector exchanges and cooperation are a framework supporting bilateral relations. I welcome the fact that, taking the opportunity of President Yoon's visit to Japan, economic federations in both Japan and the ROK have announced they will each establish a fund for future-oriented Japan-ROK cooperation and exchange. The Government of Japan will continue to support exchanges among young people, who will hold the key to our nations' futures. Exchanges between our two countries have now recovered, and as for the number of foreign visitors to our two countries, it is ROK and Japanese nationals that are each visiting the other's country in the greatest number. I very much look forward to a further acceleration of the virtuous cycle of increasingly active people-to-people exchanges and improvements in our relations. President Yoon and I also shared a common recognition of the current harsh security environment. In particular, with regard to responses to North Korea, which is further pursuing nuclear and missile activities, including this morning's launch of an ICBM-class ballistic missile, we confirmed the importance of further reinforcing the deterrence and response capabilities of the Japan-U.S. President Yoon also expressed strong support once again regarding the abductions issue. Moreover, we reaffirmed the importance of bringing about a free and open Indo-Pacific at this historic turning point, and we shared a common recognition of the importance of like-minded countries working together to fully defend the free and open international order based on the rule of law. This visit by President Yoon to Japan has been a major step forward for the normalization of Japan-ROK relations. I am looking forward to the opportunity to speak in even greater depth with President Yoon and the First Lady at the dinner scheduled to take place after this. With President Yoon's visit to Japan as a turning point, I have high hopes for us to cultivate our trust and friendship and for Japan-ROK relations to make great strides forward. More Related Link Photos (PM in Action) Summary Japanese Tweet Archives (Archived entries for the 101st through 103rd Prime Ministers) The 103rd Prime Minister ISHIBA Shigeru Open Close 2025 2024 The 102nd Prime Minister ISHIBA Shigeru Open Close 2024 The 101st Prime Minister KISHIDA Fumio Open Close 2024 2023 2022 2021 Tag List View All Related Pages Return to the Speeches and Statements by the Prime Minister | N4: FORCED_LABOR | O4: HISTORICAL_RECOGNITION_GENERAL | P4: 1 | Q4: 1 | R4: 1 | S4: HIGH | T4: 0 | U4: 1 | V4: 0 | W4: 0 | X4: 1 | Y4: 0 | Z4: UNSPECIFIED | AA4: 0 | AB4: MIXED | AC4: en | AD4: 1 | AE4: https://japan.kantei.go.jp/101_kishida/statement/202303/_00010.html | AF4: NA | AG4: NA | AH4: NA | AI4: Opening statement, joint press conference with ROK President Yoon Suk Yeol marking the restart of "shuttle diplomacy" (first bilateral visit in ~12 years). Confirms Japan "takes up in its entirety the position of previous cabinets on the recognition of the history, including the Japan-ROK Joint Declaration announced in October 1998" -- by reference only, no apology/remorse language re-quoted directly. Coded from the opening statement only; the source page may contain a following Q&A section not captured by the automated Q&A splitter (no "Question:"-style markers) -- flagged for a follow-up pass. | AJ4: HIGH | AK4: 572c38b4-5546-595a-afd6-e20a9c92e73a | AL4: 1
A5: ea95870d-a541-41ec-b5dd-f5683284710e | B5: japan | C5: 2023-08-15 | D5: 2023 | E5: KISHIDA Fumio | F5: Prime Minister of Japan | G5: HEAD | H5: Prime Minister's Office of Japan (Kantei) | I5: SPEECH | J5: Address by Prime Minister Kishida at the Seventy-Eighth National Memorial Ceremony for the War Dead (Speeches and Statements <br>by the Prime Minister) | Prime Minister's Office of Japan | L5: Address by Prime Minister Kishida at the Seventy-Eighth National Memorial Ceremony for the War Dead (Speeches and Statements <br>by the Prime Minister) | Prime Minister's Office of Japan Address by Prime Minister Kishida at the Seventy-Eighth National Memorial Ceremony for the War Dead August 15, 2023 Tweet [Provisional translation] In the gracious presence of Their Majesties the Emperor and Empress, and with the attendance of bereaved families of the war dead, distinguished representatives of all sectors of society, and many others, I hereby commence the annual National Memorial Ceremony for the War Dead. More than three million of our compatriots lost their lives during the war. Some fell on the battlefields worrying about the future of their homeland and wishing for the happiness of their families. Others perished in remote foreign countries after the war. And many fell victim to the atomic bombings of Hiroshima and Nagasaki, the air raids on numerous cities, and the ground battles in Okinawa, among others. Here, before the souls of all who lost their lives, I offer my heartfelt prayers for their repose. We will not forget, even for a moment, that the peace and prosperity that Japan enjoys today was built atop the precious lives and the history of suffering of the war dead. I express my deepest respect and gratitude once more. Never will we forget the large number of war dead whose remains have still not been recovered. Taking it as the responsibility of the nation, we shall continue to spare no effort to collect the remains of the war dead in an intensive manner and bring them back to their hometowns at the earliest possible time. Since the end of the war, Japan has consistently walked the path of a peace-loving nation. Taking the lessons of history deeply into our hearts, we have made all possible efforts for world peace and prosperity. We must never again repeat the devastation of war. We will remain committed to this resolute pledge. In this world in which conflicts have not yet ceased, under the banner of “Proactive Contribution to Peace,” Japan is determined to join forces with the international community and do its utmost to resolve the various challenges facing the world. We shall carve out the future of our nation for the sake of the present generations and the generations of the future. I will conclude my address by once again offering my heartfelt prayers for the repose of the souls of the war dead and for the happiness of the members of their bereaved families. KISHIDA Fumio Prime Minister of Japan August 15, 2023 More Related Link Japanese Tweet Archives (Archived entries for the 101st through 103rd Prime Ministers) The 103rd Prime Minister ISHIBA Shigeru Open Close 2025 2024 The 102nd Prime Minister ISHIBA Shigeru Open Close 2024 The 101st Prime Minister KISHIDA Fumio Open Close 2024 2023 2022 2021 Tag List View All Return to the Speeches and Statements by the Prime Minister | M5: Address by Prime Minister Kishida at the Seventy-Eighth National Memorial Ceremony for the War Dead (Speeches and Statements <br>by the Prime Minister) | Prime Minister's Office of Japan Address by Prime Minister Kishida at the Seventy-Eighth National Memorial Ceremony for the War Dead August 15, 2023 Tweet [Provisional translation] In the gracious presence of Their Majesties the Emperor and Empress, and with the attendance of bereaved families of the war dead, distinguished representatives of all sectors of society, and many others, I hereby commence the annual National Memorial Ceremony for the War Dead. More than three million of our compatriots lost their lives during the war. Some fell on the battlefields worrying about the future of their homeland and wishing for the happiness of their families. Others perished in remote foreign countries after the war. And many fell victim to the atomic bombings of Hiroshima and Nagasaki, the air raids on numerous cities, and the ground battles in Okinawa, among others. Here, before the souls of all who lost their lives, I offer my heartfelt prayers for their repose. We will not forget, even for a moment, that the peace and prosperity that Japan enjoys today was built atop the precious lives and the history of suffering of the war dead. I express my deepest respect and gratitude once more. Never will we forget the large number of war dead whose remains have still not been recovered. Taking it as the responsibility of the nation, we shall continue to spare no effort to collect the remains of the war dead in an intensive manner and bring them back to their hometowns at the earliest possible time. Since the end of the war, Japan has consistently walked the path of a peace-loving nation. Taking the lessons of history deeply into our hearts, we have made all possible efforts for world peace and prosperity. We must never again repeat the devastation of war. We will remain committed to this resolute pledge. In this world in which conflicts have not yet ceased, under the banner of “Proactive Contribution to Peace,” Japan is determined to join forces with the international community and do its utmost to resolve the various challenges facing the world. We shall carve out the future of our nation for the sake of the present generations and the generations of the future. I will conclude my address by once again offering my heartfelt prayers for the repose of the souls of the war dead and for the happiness of the members of their bereaved families. KISHIDA Fumio Prime Minister of Japan August 15, 2023 More Related Link Japanese Tweet Archives (Archived entries for the 101st through 103rd Prime Ministers) The 103rd Prime Minister ISHIBA Shigeru Open Close 2025 2024 The 102nd Prime Minister ISHIBA Shigeru Open Close 2024 The 101st Prime Minister KISHIDA Fumio Open Close 2024 2023 2022 2021 Tag List View All Return to the Speeches and Statements by the Prime Minister | N5: WAR_GENERAL | O5: NA | P5: 0 | Q5: 1 | R5: 0 | S5: MEDIUM | T5: 0 | U5: 0 | V5: 0 | W5: 1 | X5: 1 | Y5: 0 | Z5: UNSPECIFIED | AA5: 0 | AB5: DOMESTIC | AC5: en | AD5: 1 | AE5: https://japan.kantei.go.jp/101_kishida/statement/202308/15shikiji.html | AF5: NA | AG5: NA | AH5: NA | AI5: 78th National Memorial Ceremony for the War Dead. Same pattern as 2022. | AJ5: MEDIUM | AK5: dd35d14a-9e02-57bc-a3d8-9c2909307f26 | AL5: 1
A6: 6a6bdd86-6ab9-453b-917b-82e8da839b94 | B6: japan | C6: 2024-08-15 | D6: 2024 | E6: KISHIDA Fumio | F6: Prime Minister of Japan | G6: HEAD | H6: Prime Minister's Office of Japan (Kantei) | I6: SPEECH | J6: Address by Prime Minister Kishida at the Seventy-Ninth National Memorial Ceremony for the War Dead (Speeches and Statements <br>by the Prime Minister) | Prime Minister's Office of Japan | L6: Address by Prime Minister Kishida at the Seventy-Ninth National Memorial Ceremony for the War Dead (Speeches and Statements <br>by the Prime Minister) | Prime Minister's Office of Japan Address by Prime Minister Kishida at the Seventy-Ninth National Memorial Ceremony for the War Dead August 15, 2024 Tweet [Provisional translation] In the gracious presence of Their Majesties the Emperor and Empress, and with the attendance of bereaved families of the war dead, distinguished representatives of all sectors of society, and many others, I hereby commence the annual National Memorial Ceremony for the War Dead. More than three million of our compatriots lost their lives during the war. Some fell on the battlefields worrying about the future of their homeland and wishing for the happiness of their families. Others perished in remote foreign countries after the war. And many fell victim to the atomic bombings of Hiroshima and Nagasaki, the air raids on numerous cities, and the ground battles in Okinawa, among others. Here, before the souls of all who lost their lives, I offer my heartfelt prayers for their repose. We will not forget, even for a moment, that the peace and prosperity that Japan enjoys today was built atop the precious lives and the history of suffering of the war dead. I express my deepest respect and gratitude once more. Never will we forget the large number of war dead whose remains have still not been recovered. We will continue to spare no effort to collect the remains of the war dead in an intensive manner and return them to their hometowns at the earliest possible time, taking it as the responsibility of the nation. Since the end of the war, Japan has consistently walked the path of a peace-loving nation. Taking the lessons of history deeply into our hearts, we have made all possible efforts for world peace and prosperity. We must never again repeat the devastation of war. Although 79 years have now passed, no matter how time flows, we will remain committed to this resolute pledge, passing it down across generations. In this world in which tragic conflicts have not yet ceased, Japan will do its utmost to resolve the various challenges facing the world as it works to maintain and strengthen the free and open international order based on the rule of law while placing human dignity at the very center. In this way we will carve out the future of our nation. I will conclude my address by once again offering my heartfelt prayers for the repose of the souls of the war dead and for the happiness of the members of their bereaved families. KISHIDA Fumio Prime Minister of Japan August 15, 2024 More Related Link Japanese Tweet Archives (Archived entries for the 101st through 103rd Prime Ministers) The 103rd Prime Minister ISHIBA Shigeru Open Close 2025 2024 The 102nd Prime Minister ISHIBA Shigeru Open Close 2024 The 101st Prime Minister KISHIDA Fumio Open Close 2024 2023 2022 2021 Tag List View All Return to the Speeches and Statements by the Prime Minister | M6: Address by Prime Minister Kishida at the Seventy-Ninth National Memorial Ceremony for the War Dead (Speeches and Statements <br>by the Prime Minister) | Prime Minister's Office of Japan Address by Prime Minister Kishida at the Seventy-Ninth National Memorial Ceremony for the War Dead August 15, 2024 Tweet [Provisional translation] In the gracious presence of Their Majesties the Emperor and Empress, and with the attendance of bereaved families of the war dead, distinguished representatives of all sectors of society, and many others, I hereby commence the annual National Memorial Ceremony for the War Dead. More than three million of our compatriots lost their lives during the war. Some fell on the battlefields worrying about the future of their homeland and wishing for the happiness of their families. Others perished in remote foreign countries after the war. And many fell victim to the atomic bombings of Hiroshima and Nagasaki, the air raids on numerous cities, and the ground battles in Okinawa, among others. Here, before the souls of all who lost their lives, I offer my heartfelt prayers for their repose. We will not forget, even for a moment, that the peace and prosperity that Japan enjoys today was built atop the precious lives and the history of suffering of the war dead. I express my deepest respect and gratitude once more. Never will we forget the large number of war dead whose remains have still not been recovered. We will continue to spare no effort to collect the remains of the war dead in an intensive manner and return them to their hometowns at the earliest possible time, taking it as the responsibility of the nation. Since the end of the war, Japan has consistently walked the path of a peace-loving nation. Taking the lessons of history deeply into our hearts, we have made all possible efforts for world peace and prosperity. We must never again repeat the devastation of war. Although 79 years have now passed, no matter how time flows, we will remain committed to this resolute pledge, passing it down across generations. In this world in which tragic conflicts have not yet ceased, Japan will do its utmost to resolve the various challenges facing the world as it works to maintain and strengthen the free and open international order based on the rule of law while placing human dignity at the very center. In this way we will carve out the future of our nation. I will conclude my address by once again offering my heartfelt prayers for the repose of the souls of the war dead and for the happiness of the members of their bereaved families. KISHIDA Fumio Prime Minister of Japan August 15, 2024 More Related Link Japanese Tweet Archives (Archived entries for the 101st through 103rd Prime Ministers) The 103rd Prime Minister ISHIBA Shigeru Open Close 2025 2024 The 102nd Prime Minister ISHIBA Shigeru Open Close 2024 The 101st Prime Minister KISHIDA Fumio Open Close 2024 2023 2022 2021 Tag List View All Return to the Speeches and Statements by the Prime Minister | N6: WAR_GENERAL | O6: NA | P6: 0 | Q6: 1 | R6: 0 | S6: MEDIUM | T6: 0 | U6: 0 | V6: 0 | W6: 1 | X6: 1 | Y6: 0 | Z6: UNSPECIFIED | AA6: 0 | AB6: DOMESTIC | AC6: en | AD6: 1 | AE6: https://japan.kantei.go.jp/101_kishida/statement/202408/15shikiji.html | AF6: NA | AG6: NA | AH6: NA | AI6: 79th National Memorial Ceremony for the War Dead. Adds "human dignity" / "free and open international order" framing; still no apology/remorse toward foreign victims. | AJ6: MEDIUM | AK6: 93f33e5f-3eee-57cb-ba7f-d3a247a4160f | AL6: 1
A7: faf66366-9100-4ce8-aff8-5dc9657eadfe | B7: japan | C7: 2025-08-15 | D7: 2025 | E7: ISHIBA Shigeru | F7: Prime Minister of Japan | G7: HEAD | H7: Prime Minister's Office of Japan (Kantei) | I7: PRESS_CONFERENCE | J7: Press Conference by Prime Minister ISHIBA Shigeru regarding the Address He Delivered at the National Memorial Ceremony for the War Dead and Other Matters (Speeches and Statements <br>by the Prime Minister) | Prime Minister's Office of Japan | L7: Press Conference by Prime Minister ISHIBA Shigeru regarding the Address He Delivered at the National Memorial Ceremony for the War Dead and Other Matters (Speeches and Statements <br>by the Prime Minister) | Prime Minister's Office of Japan Press Conference by Prime Minister ISHIBA Shigeru regarding the Address He Delivered at the National Memorial Ceremony for the War Dead and Other Matters August 15, 2025 Tweet [Provisional translation] (On why, in the address he delivered at the National Memorial Ceremony for the War Dead, Prime Minister Ishiba used the word "remorse" when stating that Japan must take remorse and also the lessons learned from that war deeply to heart, in the context of that word being used by the prime minister during that address for the first time in 13 years; on when, and in what format, Prime Minister Ishiba intends to release a message to mark the passing of 80 years since the end of the war) At today's ceremony, I delivered my remarks with the aims of offering my heartfelt condolences to all the war dead, and also of handing down across generations the sorrowful memories of the war once again, in consideration of the fact that 80 years have now passed since the war ended and generations with no firsthand experience of war now make up the great majority. Another aim I had was to state we will continue to make all possible efforts for world peace and prosperity while never again repeating the horrors of war. As for using the word "remorse" in my address, I believe that lessons to be learned arise through remorse -- one feels remorse and then lessons emerge from that. It is not the case that lessons to be learned suddenly appear out of nowhere. So my personal philosophy on the matter is that remorse comes first, and after that, lessons to be learned will come to light. In that sense we could say that it forms an interconnected whole. I do not believe that thinking is in any way different from the views and the thinking held by the Government until now. I made that statement intending to express the need for us to take deeply into our hearts once again our remorse and also the lessons learned, so that we never again repeat such a war. As for a message marking 80 years since the end of the war, if I may speak hypothetically, my cabinet would maintain overall the position held by previous administrations with regard to our recognition of history, including the official statements made by prime ministers over the years. We would carry that into the future. As for what the message for the 80th anniversary year would entail, as of right now, nothing has been decided in concrete terms. As I stated recently in the Diet in response to a question, I will make an appropriate decision on the matter giving due consideration to the official statements released by prime ministers over the years. If I were to release a message, I would consider it important to come from the perspective that we must not allow memories of the war to fade, and that such a war must never be repeated. Building upon the official statements made by prime ministers until now, I would also consider one of the significant aspects to be articulating a message regarding the matters raised in those statements as well as things we must contemplate. But it is not the case that the specific contents of any such message have been decided. Related Link Japanese Tweet Return to the Speeches and Statements by the Prime Minister | M7: Press Conference by Prime Minister ISHIBA Shigeru regarding the Address He Delivered at the National Memorial Ceremony for the War Dead and Other Matters (Speeches and Statements <br>by the Prime Minister) | Prime Minister's Office of Japan Press Conference by Prime Minister ISHIBA Shigeru regarding the Address He Delivered at the National Memorial Ceremony for the War Dead and Other Matters August 15, 2025 Tweet [Provisional translation] (On why, in the address he delivered at the National Memorial Ceremony for the War Dead, Prime Minister Ishiba used the word "remorse" when stating that Japan must take remorse and also the lessons learned from that war deeply to heart, in the context of that word being used by the prime minister during that address for the first time in 13 years; on when, and in what format, Prime Minister Ishiba intends to release a message to mark the passing of 80 years since the end of the war) At today's ceremony, I delivered my remarks with the aims of offering my heartfelt condolences to all the war dead, and also of handing down across generations the sorrowful memories of the war once again, in consideration of the fact that 80 years have now passed since the war ended and generations with no firsthand experience of war now make up the great majority. Another aim I had was to state we will continue to make all possible efforts for world peace and prosperity while never again repeating the horrors of war. As for using the word "remorse" in my address, I believe that lessons to be learned arise through remorse -- one feels remorse and then lessons emerge from that. It is not the case that lessons to be learned suddenly appear out of nowhere. So my personal philosophy on the matter is that remorse comes first, and after that, lessons to be learned will come to light. In that sense we could say that it forms an interconnected whole. I do not believe that thinking is in any way different from the views and the thinking held by the Government until now. I made that statement intending to express the need for us to take deeply into our hearts once again our remorse and also the lessons learned, so that we never again repeat such a war. As for a message marking 80 years since the end of the war, if I may speak hypothetically, my cabinet would maintain overall the position held by previous administrations with regard to our recognition of history, including the official statements made by prime ministers over the years. We would carry that into the future. As for what the message for the 80th anniversary year would entail, as of right now, nothing has been decided in concrete terms. As I stated recently in the Diet in response to a question, I will make an appropriate decision on the matter giving due consideration to the official statements released by prime ministers over the years. If I were to release a message, I would consider it important to come from the perspective that we must not allow memories of the war to fade, and that such a war must never be repeated. Building upon the official statements made by prime ministers until now, I would also consider one of the significant aspects to be articulating a message regarding the matters raised in those statements as well as things we must contemplate. But it is not the case that the specific contents of any such message have been decided. | N7: HISTORICAL_RECOGNITION_GENERAL | O7: WAR_GENERAL | P7: 1 | Q7: 1 | R7: 1 | S7: HIGH | T7: 0 | U7: 1 | V7: 1 | W7: 1 | X7: 0 | Y7: 0 | Z7: STATE | AA7: 0 | AB7: MIXED | AC7: en | AD7: 1 | AE7: https://japan.kantei.go.jp/103/statement/202508/15kaiken.html | AF7: NA | AG7: NA | AH7: NA | AI7: Same-day press conference where Ishiba is asked directly why he used "remorse" for the first time in 13 years, and whether/when he will issue an 80th-anniversary statement. He explicitly says his Cabinet "would maintain overall the position held by previous administrations with regard to our recognition of history, including the official statements made by prime ministers over the years" and that nothing on a possible anniversary statement has been decided. High-value record for tracking continuity/change in Japan's official historical-recognition posture. | AJ7: HIGH | AK7: 65c1d6c7-b98a-5355-a64f-2c88296af848 | AL7: 1
A8: 6d0a0699-97fe-47d9-a5bd-94833e57b5fe | B8: japan | C8: 2025-08-15 | D8: 2025 | E8: ISHIBA Shigeru | F8: Prime Minister of Japan | G8: HEAD | H8: Prime Minister's Office of Japan (Kantei) | I8: SPEECH | J8: Address by Prime Minister Ishiba at the Eightieth National Memorial Ceremony for the War Dead (Speeches and Statements <br>by the Prime Minister) | Prime Minister's Office of Japan | L8: Address by Prime Minister Ishiba at the Eightieth National Memorial Ceremony for the War Dead (Speeches and Statements <br>by the Prime Minister) | Prime Minister's Office of Japan Address by Prime Minister Ishiba at the Eightieth National Memorial Ceremony for the War Dead August 15, 2025 Tweet [Provisional translation] In the gracious presence of Their Majesties the Emperor and Empress, and with the attendance of bereaved families of the war dead, distinguished representatives of all sectors of society, and many others, I hereby commence the annual National Memorial Ceremony for the War Dead. More than three million of our compatriots lost their lives during the war. Some fell on the battlefields worrying about the future of their homeland and wishing for the happiness of their families. Many fell victim to the atomic bombings of Hiroshima and Nagasaki, the air raids and naval bombardments on numerous cities, and the ground battles in Okinawa. Others, after the war ended, died in distant foreign lands. Here, before the souls of all who lost their lives, I offer my heartfelt prayers for their repose. We will not forget, even for a moment, that the peace and prosperity that Japan enjoys today was built atop the precious lives and the history of suffering of the war dead. I express my deepest respect and gratitude once more. Never will we forget the large number of war dead whose remains have still not been recovered. We will continue to spare no effort to return them to their hometowns at the earliest possible time. Eighty years have now passed since the war ended. Today, generations with no firsthand experience of war make up the great majority. We must never again repeat the horrors of war. We must never again lose our way. We must now take deeply into our hearts once again our remorse and also the lessons learned from that war. At the same time, over the past 80 years, Japan has consistently walked the path of a peace-loving nation and made all possible efforts for world peace and prosperity. No matter how much time passes, we will hand down across generations the sorrowful memories of the war and our resolute pledge to renounce war, and we will remain steadfast in our actions to foster lasting peace. In this world in which tragic conflicts rage on, Japan will, by rejecting division and cultivating tolerance, pave the way to a better tomorrow for the sake of both present and future generations. I will conclude my address by once again offering my heartfelt prayers for the repose of the souls of the war dead and for the happiness of the members of their bereaved families. ISHIBA Shigeru Prime Minister of Japan August 15, 2025 Related Link Japanese Tweet Return to the Speeches and Statements by the Prime Minister | M8: Address by Prime Minister Ishiba at the Eightieth National Memorial Ceremony for the War Dead (Speeches and Statements <br>by the Prime Minister) | Prime Minister's Office of Japan Address by Prime Minister Ishiba at the Eightieth National Memorial Ceremony for the War Dead August 15, 2025 Tweet [Provisional translation] In the gracious presence of Their Majesties the Emperor and Empress, and with the attendance of bereaved families of the war dead, distinguished representatives of all sectors of society, and many others, I hereby commence the annual National Memorial Ceremony for the War Dead. More than three million of our compatriots lost their lives during the war. Some fell on the battlefields worrying about the future of their homeland and wishing for the happiness of their families. Many fell victim to the atomic bombings of Hiroshima and Nagasaki, the air raids and naval bombardments on numerous cities, and the ground battles in Okinawa. Others, after the war ended, died in distant foreign lands. Here, before the souls of all who lost their lives, I offer my heartfelt prayers for their repose. We will not forget, even for a moment, that the peace and prosperity that Japan enjoys today was built atop the precious lives and the history of suffering of the war dead. I express my deepest respect and gratitude once more. Never will we forget the large number of war dead whose remains have still not been recovered. We will continue to spare no effort to return them to their hometowns at the earliest possible time. Eighty years have now passed since the war ended. Today, generations with no firsthand experience of war make up the great majority. We must never again repeat the horrors of war. We must never again lose our way. We must now take deeply into our hearts once again our remorse and also the lessons learned from that war. At the same time, over the past 80 years, Japan has consistently walked the path of a peace-loving nation and made all possible efforts for world peace and prosperity. No matter how much time passes, we will hand down across generations the sorrowful memories of the war and our resolute pledge to renounce war, and we will remain steadfast in our actions to foster lasting peace. In this world in which tragic conflicts rage on, Japan will, by rejecting division and cultivating tolerance, pave the way to a better tomorrow for the sake of both present and future generations. I will conclude my address by once again offering my heartfelt prayers for the repose of the souls of the war dead and for the happiness of the members of their bereaved families. ISHIBA Shigeru Prime Minister of Japan August 15, 2025 Related Link Japanese Tweet Return to the Speeches and Statements by the Prime Minister | N8: WAR_GENERAL | O8: HISTORICAL_RECOGNITION_GENERAL | P8: 1 | Q8: 1 | R8: 0 | S8: MEDIUM | T8: 0 | U8: 0 | V8: 1 | W8: 1 | X8: 1 | Y8: 0 | Z8: UNSPECIFIED | AA8: 0 | AB8: DOMESTIC | AC8: en | AD8: 1 | AE8: https://japan.kantei.go.jp/103/statement/202508/15shikiji.html | AF8: NA | AG8: NA | AH8: NA | AI8: 80th National Memorial Ceremony for the War Dead. Notable: first use of the word "remorse" in this annual address in 13 years (see companion press conference same day) -- "we must now take deeply into our hearts once again our remorse and also the lessons learned from that war." Still agentless/general (does not name Japan or specific foreign victims as the object of remorse) -- coded agency_explicit=0 on that basis; flag for review as this is a genuinely borderline call given the significance of reintroducing "remorse." | AJ8: MEDIUM | AK8: eebad3b7-7af8-50d4-93c7-ab295412b511 | AL8: 1
A9: 4bc72084-d0ff-41c3-accd-fc21ca848cef | B9: japan | C9: 2020-08-15 | D9: 2020 | E9: ABE Shinzo | F9: Prime Minister of Japan | G9: HEAD | H9: Prime Minister's Office of Japan (Kantei) | I9: SPEECH | J9: Address by the Prime Minister at the Seventy-Fifth National Memorial Ceremony for the War Dead (Speeches and Statements by the Prime Minister) | Prime Minister of Japan and His Cabinet | L9: Address by the Prime Minister at the Seventy-Fifth National Memorial Ceremony for the War Dead (Speeches and Statements by the Prime Minister) | Prime Minister of Japan and His Cabinet Skip to main content Home News Videos Policy The Cabinet Links Home > News > Speeches and Statements by the Prime Minister > August 2020 > Address by the Prime Minister at the Seventy-Fifth National Memorial Ceremony for the War Dead Speeches and Statements by the Prime Minister Address by the Prime Minister at the Seventy-Fifth National Memorial Ceremony for the War Dead August 15, 2020 Tweet [Provisional Translation] In the gracious presence of Their Majesties the Emperor and Empress, and with the attendance of bereaved families of the war dead and distinguished representatives of all sectors of society, I hereby commence the annual National Memorial Ceremony for the War Dead. More than three million of our compatriots lost their lives during the war, which was extremely fierce and harsh. Some fell on the battlefields worrying about the future of their homeland and wishing for the happiness of their families. Others perished in remote foreign countries after the war. The atomic bombings of Hiroshima and Nagasaki, the air raids on Tokyo and other cities, and the ground battles in Okinawa, among others, took a heavy toll without mercy. Here, before the souls of all who lost their lives, I offer my heartfelt prayers for their repose. Again now on the 75th anniversary of the end of the war, we will never forget that the peace and prosperity we enjoy today was built atop the precious sacrifices of the war dead. I express my deepest respect and gratitude once more. Never will we forget the large number of war dead whose remains have still not been recovered. Taking it as the responsibility of the nation, we shall spare no effort to enable their remains to return to their hometowns at the earliest possible time. Over the 75 years since the end of the war, Japan has consistently walked the path of a country that values peace. We have worked to the very best of our ability to transform the world into a better place. We must never again repeat the devastation of war. We will continue to remain committed to this resolute pledge. Under the banner of "Proactive Contribution to Peace," we are determined to join hands with the international community and play a greater role than ever before in resolving the various challenges facing the world. We shall overcome the current novel coronavirus disease (COVID-19) and carve out the future of our nation for the sake of the generation alive now and the generations of tomorrow. I will conclude my address by once again offering my heartfelt prayers for the repose of the souls of the war dead and for the happiness of the members of their bereaved families. ABE Shinzo Prime Minister of Japan August 15, 2020 Related Link Japanese Home News Videos Policy The Cabinet Links Cabinet Public Affairs Office, Cabinet Secretariat, 1-6-1 Nagata-cho, Chiyoda-ku, Tokyo 100 - 8968, Japan Copyright© Cabinet Public Affairs Office, Cabinet Secretariat. All Rights Reserved. | M9: Address by the Prime Minister at the Seventy-Fifth National Memorial Ceremony for the War Dead (Speeches and Statements by the Prime Minister) | Prime Minister of Japan and His Cabinet Skip to main content Home News Videos Policy The Cabinet Links Home > News > Speeches and Statements by the Prime Minister > August 2020 > Address by the Prime Minister at the Seventy-Fifth National Memorial Ceremony for the War Dead Speeches and Statements by the Prime Minister Address by the Prime Minister at the Seventy-Fifth National Memorial Ceremony for the War Dead August 15, 2020 Tweet [Provisional Translation] In the gracious presence of Their Majesties the Emperor and Empress, and with the attendance of bereaved families of the war dead and distinguished representatives of all sectors of society, I hereby commence the annual National Memorial Ceremony for the War Dead. More than three million of our compatriots lost their lives during the war, which was extremely fierce and harsh. Some fell on the battlefields worrying about the future of their homeland and wishing for the happiness of their families. Others perished in remote foreign countries after the war. The atomic bombings of Hiroshima and Nagasaki, the air raids on Tokyo and other cities, and the ground battles in Okinawa, among others, took a heavy toll without mercy. Here, before the souls of all who lost their lives, I offer my heartfelt prayers for their repose. Again now on the 75th anniversary of the end of the war, we will never forget that the peace and prosperity we enjoy today was built atop the precious sacrifices of the war dead. I express my deepest respect and gratitude once more. Never will we forget the large number of war dead whose remains have still not been recovered. Taking it as the responsibility of the nation, we shall spare no effort to enable their remains to return to their hometowns at the earliest possible time. Over the 75 years since the end of the war, Japan has consistently walked the path of a country that values peace. We have worked to the very best of our ability to transform the world into a better place. We must never again repeat the devastation of war. We will continue to remain committed to this resolute pledge. Under the banner of "Proactive Contribution to Peace," we are determined to join hands with the international community and play a greater role than ever before in resolving the various challenges facing the world. We shall overcome the current novel coronavirus disease (COVID-19) and carve out the future of our nation for the sake of the generation alive now and the generations of tomorrow. I will conclude my address by once again offering my heartfelt prayers for the repose of the souls of the war dead and for the happiness of the members of their bereaved families. ABE Shinzo Prime Minister of Japan August 15, 2020 Related Link Japanese Home News Videos Policy The Cabinet Links Cabinet Public Affairs Office, Cabinet Secretariat, 1-6-1 Nagata-cho, Chiyoda-ku, Tokyo 100 - 8968, Japan Copyright© Cabinet Public Affairs Office, Cabinet Secretariat. All Rights Reserved. | N9: WAR_GENERAL | O9: NA | P9: 0 | Q9: 1 | R9: 0 | S9: MEDIUM | T9: 0 | U9: 0 | V9: 0 | W9: 1 | X9: 1 | Y9: 0 | Z9: UNSPECIFIED | AA9: 0 | AB9: DOMESTIC | AC9: en | AD9: 1 | AE9: https://japan.kantei.go.jp/98_abe/statement/202008/_00003.html | AF9: NA | AG9: NA | AH9: NA | AI9: 75th National Memorial Ceremony for the War Dead. Domestic mourning address for Japan's own war dead; no apology/remorse toward foreign victims; "responsibility of the nation" refers to remains repatriation, not war-causing responsibility. remedy=1 refers to the remains-repatriation program (directed at Japan's own bereaved families, not foreign victims -- noted for coder review). | AJ9: MEDIUM | AK9: 671e0049-f3ab-5fcc-947b-8886e29b704e | AL9: 1
A10: 67f3aa0d-c086-4894-b5e5-e70e1b091f0c | B10: japan | C10: 2021-01-08 | D10: 2021 | E10: SUGA Yoshihide | F10: Prime Minister of Japan | G10: HEAD | H10: Prime Minister's Office of Japan (Kantei) | I10: PRESS_CONFERENCE | J10: Press Conference by the Prime Minister on the court case brought by a group of former comfort women (Speeches and Statements by the Prime Minister) | Prime Minister of Japan and His Cabinet | L10: Press Conference by the Prime Minister on the court case brought by a group of former comfort women (Speeches and Statements by the Prime Minister) | Prime Minister of Japan and His Cabinet Skip to main content Home News Videos Policy The Cabinet Links Home > News > Speeches and Statements by the Prime Minister > January 2021 > Press Conference by the Prime Minister on the court case brought by a group of former comfort women Speeches and Statements by the Prime Minister Press Conference by the Prime Minister on the court case brought by a group of former comfort women January 8, 2021 Tweet [Provisional Translation] (On the court case brought by a group of former comfort women in the Republic of Korea) First and foremost, under international law, sovereign states are immune from the jurisdiction of foreign courts. Since that is well-established, we believe that this suit must be dismissed. The issue of comfort women between Japan and the Republic of Korea is already settled completely and finally, through the 1965 Agreement on the Settlement of Problems concerning Property and Claims and on Economic Cooperation. We strongly demand that the ROK take measures to remedy breaches of international law. Such a ruling is totally unacceptable in light of Japan's position. (On the intrusion by rioters at the U.S. Capitol) I hope the citizens of the United States will unite and move on under President-elect Biden. (On the future responses regarding Japan-ROK relations) Firstly, this case must be dismissed. That must be the starting point. Related Link Japanese Home News Videos Policy The Cabinet Links Cabinet Public Affairs Office, Cabinet Secretariat, 1-6-1 Nagata-cho, Chiyoda-ku, Tokyo 100 - 8968, Japan Copyright© Cabinet Public Affairs Office, Cabinet Secretariat. All Rights Reserved. | M10: Press Conference by the Prime Minister on the court case brought by a group of former comfort women (Speeches and Statements by the Prime Minister) | Prime Minister of Japan and His Cabinet Skip to main content Home News Videos Policy The Cabinet Links Home > News > Speeches and Statements by the Prime Minister > January 2021 > Press Conference by the Prime Minister on the court case brought by a group of former comfort women Speeches and Statements by the Prime Minister Press Conference by the Prime Minister on the court case brought by a group of former comfort women January 8, 2021 Tweet [Provisional Translation] (On the court case brought by a group of former comfort women in the Republic of Korea) First and foremost, under international law, sovereign states are immune from the jurisdiction of foreign courts. Since that is well-established, we believe that this suit must be dismissed. The issue of comfort women between Japan and the Republic of Korea is already settled completely and finally, through the 1965 Agreement on the Settlement of Problems concerning Property and Claims and on Economic Cooperation. We strongly demand that the ROK take measures to remedy breaches of international law. Such a ruling is totally unacceptable in light of Japan's position. | N10: COMFORT_WOMEN | O10: COMPENSATION_REPARATION | P10: 1 | Q10: 1 | R10: 1 | S10: HIGH | T10: 0 | U10: 1 | V10: 0 | W10: 0 | X10: 1 | Y10: 0 | Z10: UNSPECIFIED | AA10: 0 | AB10: MIXED | AC10: en | AD10: 1 | AE10: https://japan.kantei.go.jp/99_suga/statement/202101/_00004.html | AF10: NA | AG10: NA | AH10: NA | AI10: Suga's response to the Seoul Central District Court ruling ordering Japan to pay compensation to former comfort women. Asserts sovereign immunity and that the issue is "already settled completely and finally" via the 1965 Agreement; demands the ROK "take measures to remedy breaches of international law." A denial/closure-framing statement rather than an apology -- remedy=1 refers to the pre-existing 1965 Agreement being invoked as the settlement mechanism, not a new remedy offered here. | AJ10: HIGH | AK10: eeb64e05-d5db-505f-af4c-561e7108ba3e | AL10: 1
A11: cf65781c-248e-490c-9711-d8e5d039f43d | B11: japan | C11: 2021-08-15 | D11: 2021 | E11: SUGA Yoshihide | F11: Prime Minister of Japan | G11: HEAD | H11: Prime Minister's Office of Japan (Kantei) | I11: SPEECH | J11: Address by the Prime Minister at the Seventy-Sixth National Memorial Ceremony for the War Dead (Speeches and Statements by the Prime Minister) | Prime Minister of Japan and His Cabinet | L11: Address by the Prime Minister at the Seventy-Sixth National Memorial Ceremony for the War Dead (Speeches and Statements by the Prime Minister) | Prime Minister of Japan and His Cabinet Skip to main content Home News Videos Policy The Cabinet Links Home > News > Speeches and Statements by the Prime Minister > August 2021 > Address by the Prime Minister at the Seventy-Sixth National Memorial Ceremony for the War Dead Speeches and Statements by the Prime Minister Address by the Prime Minister at the Seventy-Sixth National Memorial Ceremony for the War Dead August 15, 2021 Tweet [Provisional translation] In the gracious presence of Their Majesties the Emperor and Empress, and with the attendance of bereaved families of the war dead and distinguished representatives of all sectors of society, I hereby commence the annual National Memorial Ceremony for the War Dead. More than three million of our compatriots lost their lives during the war. Some fell on the battlefields worrying about the future of their homeland and wishing for the happiness of their families. Others perished in remote foreign countries after the war. And many fell victim to the violent turmoil of war in the atomic bombings of Hiroshima and Nagasaki, the air raids on numerous cities, and the ground battles in Okinawa, among others. Here, before the souls of all who lost their lives, I offer my heartfelt prayers for their repose. We will not forget, even for a moment, that the peace and prosperity we enjoy today was built atop the precious lives and the history of suffering of the war dead. I express my deepest respect and gratitude once more. Never will we forget the large number of war dead whose remains have still not been recovered. Taking it as the responsibility of the nation, we shall spare no effort to enable their remains to return to their hometowns at the earliest possible time. Since the end of the war, Japan has consistently walked the path of a country that values peace. We have made every possible effort to bring about a world in which all people around the globe can enjoy peace and live in a way rich in spirit. We will remain committed to our conviction that we must never again repeat the devastation of war. Under the banner of "Proactive Contribution to Peace," we are determined to join forces with the international community and do our utmost to resolve the various challenges facing the world. We will overcome COVID-19, which continues to spread even now, restore at the earliest possible time our vibrant daily lives in which we feel at ease, and carve out the future of our nation. I will conclude my address by once again offering my heartfelt prayers for the repose of the souls of the war dead and for the happiness of the members of their bereaved families. SUGA Yoshihide Prime Minister of Japan August 15, 2021 Related Link Japanese Home News Videos Policy The Cabinet Links Cabinet Public Affairs Office, Cabinet Secretariat, 1-6-1 Nagata-cho, Chiyoda-ku, Tokyo 100 - 8968, Japan Copyright© Cabinet Public Affairs Office, Cabinet Secretariat. All Rights Reserved. | M11: Address by the Prime Minister at the Seventy-Sixth National Memorial Ceremony for the War Dead (Speeches and Statements by the Prime Minister) | Prime Minister of Japan and His Cabinet Skip to main content Home News Videos Policy The Cabinet Links Home > News > Speeches and Statements by the Prime Minister > August 2021 > Address by the Prime Minister at the Seventy-Sixth National Memorial Ceremony for the War Dead Speeches and Statements by the Prime Minister Address by the Prime Minister at the Seventy-Sixth National Memorial Ceremony for the War Dead August 15, 2021 Tweet [Provisional translation] In the gracious presence of Their Majesties the Emperor and Empress, and with the attendance of bereaved families of the war dead and distinguished representatives of all sectors of society, I hereby commence the annual National Memorial Ceremony for the War Dead. More than three million of our compatriots lost their lives during the war. Some fell on the battlefields worrying about the future of their homeland and wishing for the happiness of their families. Others perished in remote foreign countries after the war. And many fell victim to the violent turmoil of war in the atomic bombings of Hiroshima and Nagasaki, the air raids on numerous cities, and the ground battles in Okinawa, among others. Here, before the souls of all who lost their lives, I offer my heartfelt prayers for their repose. We will not forget, even for a moment, that the peace and prosperity we enjoy today was built atop the precious lives and the history of suffering of the war dead. I express my deepest respect and gratitude once more. Never will we forget the large number of war dead whose remains have still not been recovered. Taking it as the responsibility of the nation, we shall spare no effort to enable their remains to return to their hometowns at the earliest possible time. Since the end of the war, Japan has consistently walked the path of a country that values peace. We have made every possible effort to bring about a world in which all people around the globe can enjoy peace and live in a way rich in spirit. We will remain committed to our conviction that we must never again repeat the devastation of war. Under the banner of "Proactive Contribution to Peace," we are determined to join forces with the international community and do our utmost to resolve the various challenges facing the world. We will overcome COVID-19, which continues to spread even now, restore at the earliest possible time our vibrant daily lives in which we feel at ease, and carve out the future of our nation. I will conclude my address by once again offering my heartfelt prayers for the repose of the souls of the war dead and for the happiness of the members of their bereaved families. SUGA Yoshihide Prime Minister of Japan August 15, 2021 Related Link Japanese Home News Videos Policy The Cabinet Links Cabinet Public Affairs Office, Cabinet Secretariat, 1-6-1 Nagata-cho, Chiyoda-ku, Tokyo 100 - 8968, Japan Copyright© Cabinet Public Affairs Office, Cabinet Secretariat. All Rights Reserved. | N11: WAR_GENERAL | O11: NA | P11: 0 | Q11: 1 | R11: 0 | S11: MEDIUM | T11: 0 | U11: 0 | V11: 0 | W11: 1 | X11: 1 | Y11: 0 | Z11: UNSPECIFIED | AA11: 0 | AB11: DOMESTIC | AC11: en | AD11: 1 | AE11: https://japan.kantei.go.jp/99_suga/statement/202108/_00006.html | AF11: NA | AG11: NA | AH11: NA | AI11: 76th National Memorial Ceremony for the War Dead. Same genre/pattern as the 2020 (75th) address; no apology/remorse toward foreign victims. | AJ11: MEDIUM | AK11: 5926ff7f-ab33-5fb8-af79-578cbec6ccc6 | AL11: 1
A12: ff14562b-1f5e-4786-9ca8-e650245bfdad | B12: korea | C12: 2020-08-15 | D12: 2020 | E12: Moon Jae-in | F12: President of the Republic of Korea | G12: HEAD | H12: Office of the President, Republic of Korea (via National Archives of Korea web archive) | I12: PRESS_CONFERENCE | J12: Address by President Moon Jae-in on Korea’s 75th Liberation Day | L12: Address by President Moon Jae-in on Korea’s 75th Liberation Day 컨텐츠바로가기 Skip To main Contents ﻿ 이 웹사이트는 제19대 대통령 임기 종료에 따라 대통령기록관이 「대통령기록물 관리에 관한 법률」에 의해 이관받아 서비스하는 대통령기록물입니다. 자료의 열람만 가능하며 수정 · 추가 · 삭제는 불가능합니다. 다만, 「개인정보보호법」 에 의하여 개인의 정보를 보호받기 원하시는 분은 관련 내용(요청자, 요청내용, 연락처, 글위치)을 대통령 웹기록물 담당자(044-211-2253)에게 요청해 주시면 신속히 검토하여 조치해 드리겠습니다. 감사합니다. [오늘 그만 보기] 이 웹사이트는 국민의 알권리 보장을 위해 대통령기록관에서 보존·서비스하고 있는 대통령기록물입니다. This Website is the Presidential Records maintained and serviced by the Presidential Archives of Korea to ensure the people's right to know. PRESIDENT Greetings Profile Life Story The Administration SPEECHES & REMARKS BRIEFINGS Speeches & Remarks Briefings MEDIA Interviews Korea.net News CONTENTS Infographics Photos Videos Publications CONTACT General Information Tours Search KR JP CN Twitter SPEECHES & REMARKS BRIEFINGS SPEECHES & REMARKS BRIEFING Address by President Moon Jae-in on Korea’s 75th Liberation Day August 15, 2020 Share (Unofficial Translation) Fellow Koreans, decorated independence activists, bereaved relatives of those departed and Korean compatriots abroad, As we mark the 75th Liberation Day, we contemplate the noble sacrifice and spirit of our patriotic forebears who gave their all to achieve our nation’s independence. Today’s celebration began by welcoming the surviving patriots who dedicated themselves to the cause of independence. Patriot Lim Wu-cheol is 101 years old, and the other three are almost centenarians as well. Any effort to honor them will pale in comparison to the Republic of Korea’s proud progress and esteem that every one of them helped to accomplish. There are now only 31 surviving patriotic independence activists. I would like to ask everyone to vigorously applaud those patriots here with us: Lim Wu-cheol, Kim Yeong-gwan, Lee Yeong-su and Jang Byeong-ha to express our deepest respect and gratitude. Their valued presence makes this event all the more meaningful. Our liberation was obtained by each and every Korean rising together as the rightful owners of a democratic republic. All of those who have achieved accomplishments big and small as masters of their own lives comprise the roots of what we are today. Our forebears left us a conviction that has formed an immense root of our history: “If we unite, we can prevail over any crisis.” In the process of overcoming the COVID-19 outbreak, we have been able to reaffirm our capabilities while surmounting the crisis together. Presently, massive natural disasters caused by abnormal weather conditions are threatening our everyday lives yet again. Nonetheless, we will certainly prevail over them this time as we always have. I extend my profound sympathy to everyone who has suffered damage from these catastrophes, most of all to those who lost what is most precious – life itself. We will confront disasters until they are over in order to protect the lives and property of the people. We will also do as much as we can for disaster recovery. Moreover, in preparation for extreme weather becoming increasingly severe, we will muster all available capabilities to safeguard the people’s safety, thereby sparing them from repeated suffering. I salute the decorated independence activists and bereaved families who have become a source of pride for the Republic of Korea. I promise that with the people we will weather today’s crisis and calamities without fail. Fellow Koreans, Dongdaemun Design Plaza, where we are gathered today, is built upon the site of the Joseon Dynasty’s Military Training Command and installations. Gyeongseong Stadium was built here during the Japanese colonial period and was renamed Seoul Stadium after liberation. Numerous sweat-stained historic chapters have been recorded on this site, which was long referred to as Dongdaemun Stadium. Among these, the beads of sweat shed by young Joseon marathoner Sohn Kee-chung under colonial rule must be remembered as the most ardent and regrettable. In 1935, he broke away from a field of runners in a 10,000 meter race at Gyeongseong Stadium and won. The next year, he set a world record while winning the marathon at the Berlin Olympics. As the Japanese national anthem began to play during the award ceremony, Olympic gold medalist Sohn Kee-chung hid the Japanese flag on his chest with the laurel sapling presented to him. The Korean Olympian Nam Seung-yong, who won bronze in that marathon, could only hang his head and close his eyes. They pulled off a great victory that helped restore Korean pride, but they had no country upon which to bestow that glory. Our independence movement involved reclaiming the country and, at the same time, upholding the dignity of individuals. We simultaneously achieved independence and a revolution to establish a democratic republic based on popular sovereignty. Our efforts to create a dignified country that will never again lose to anyone have never ceased even after liberation. From being the most impoverished country to receive international aid, we have soared to become one of the 10 largest global economic powerhouses. In the face of dictatorship, we left the world a milestone for democracy. Though we endured a period when individual sacrifices were demanded and human rights were oppressed in the name of the state, we have never stopped marching toward a properly functioning country where each citizen is guaranteed inherent rights for freedom, equality, dignity and safety. Our people have withstood many crises. We rose from the ashes of war and overcame the Asian foreign exchange and global financial crises. Together, we have also surmounted the crisis prompted by Japan’s export restrictions. We have actually turned that into an opportunity to leap forward as a nation that cannot be shaken. Mutually beneficial cooperation between large businesses and SMEs has led to independence in the production of materials, parts and equipment. Some of these ventures have even attracted foreign investors. We have also overcome the COVID-19 crisis through the Government, individuals, medical professionals and business leaders trusting and relying on one another. The Government has transparently disclosed all the information needed for epidemic prevention and control. The people trust the Government’s approach and have voluntarily become the principal agents in anti-epidemic efforts. Korean businesses developed the first fast and accurate COVID-19 test kit in the world. Workers have produced epidemic prevention supplies, putting their neighbors first. Medical staff, volunteers, the public and businesses brought together their respective efforts, creating a catalyst for overcoming the COVID-19 crisis and setting an example lauded by the entire world. However, we are in a situation that requires yet an even higher level of alertness. The Government will do everything possible until the situation is over to protect the people from the virus, including the securing of vaccines and early development of treatments. Our successful epidemic prevention and control – free of border closures, regional lockdowns and an economic shutdown – has helped our economy fare well. Thanks to this success, the Government’s rapid countermeasures to revive the economy through expansionary spending have been effective. Amid the global economic crisis, Korea’s economic growth this year is projected to rank first among the 37 OECD member states. Our GDP is also forecast to join the ranks of the 10 largest economies in the world. I cannot but extend my respect and gratitude to our people once again, who are turning crises into opportunities even while enduring great suffering. We have now affirmed the fact that our neighbors’ safety equals our own and are preparing for a post-COVID-19 era. While bringing implementation of the Korean New Deal into full gear, we will reform and upgrade our economic fundamentals – employing the Digital New Deal and the Green New Deal as our wings. From a fast follower-type economy to a pace-setting one and from a carbon-dependent economy to a low-carbon one, we will fundamentally transform the Republic of Korea and once again leap forward. The spirit that permeates the core of the Korean New Deal is also people-centered mutual benefit. A new social contract for mutual benefit, the Korean New Deal is also a pledge to achieve and share prosperity together by further strengthening the employment and social safety nets and increasing investments in people. What matters the most is to reduce gaps and inequality. Only when everyone is living well can we say that genuine liberation has been achieved. I believe that the people will join us on the path toward sustainable development for both their own benefit as well as that of future generations. Fellow Koreans, In the winter of 2016, squares and streets throughout the country were filled with the spirit of Article 1 of the Constitution: All state authority shall emanate from the people. Our people held aloft lit candles and once more etched onto the chapters of history the fact that the power to change the world always rests with them. That spirit became the foundation of our Administration. Today, on the occasion of the 75th anniversary of Liberation Day, I look back to see whether each individual really has achieved liberation. And I think of a country that exists to guarantee individuals’ decent lives – not one where individuals exist for it. This is also about an era marked by Article 10 of the Constitution: All citizens shall be assured of human value and dignity and have the right to pursue happiness. This is the goal that my Administration is aiming to achieve. To date, the Government has solidified our practical foundation of freedom and equality. While people exert individuality and ability to the fullest thanks to the social safety net and security in their daily lives, we have also made efforts to build a nation where individual achievements are respected by everyone. I do not believe that we can achieve all of these tasks before the end of my Administration. However, we will give people the firm belief that our society is heading in that direction and do all we can to build a solid foundation. We remember our compatriots who emigrated from the Empire of Korea to work in Hawaii and Mexico but could not return as they lost their homeland. We must never forget that tearful history. Although the motherland could not protect its people, they collected wages from labor and spoonfuls of rice to fund the Provisional Republic of Korea Government’s independence movement. As such, they became a root of the overseas independence movement. We must remember forever those who were never able to return to the arms of their families in a liberated homeland. We must ask whether the country did its due then and is doing so now for its people. The Republic of Korea has grown enough and possesses enough confidence to ensure that not even a single citizen is ever abandoned again. On April 30, 2018, three Korean sailors who were kidnapped in waters off Ghana returned to their homeland along with the Cheonghae unit aboard the destroyer that rescued them, the ROKS Munmu the Great. Also rescued safely were Koreans kidnapped by armed assailants in Libya in July 2018 and five crew members abducted in waters off Benin, West Africa, in July 2020. Despite the COVID-19 outbreak, we dispatched military aircraft to Iraq and brought back 293 Korean workers. Charter flights, military aircraft and even a presidential airplane were mobilized to help 2,000 Koreans return home safely from seven countries under serious threats from the spreading virus. The Government has safely evacuated over 46,000 Korean expatriates from 119 countries through charter flights. It was deeply meaningful to mark the centennials of the March First Independence Movement and the establishment of the Provisional Republic of Korea Government last year by repatriating the remains of five decorated independence activists. We as a nation must also respond without fail to the efforts of individuals to prove their own dignity and pool our wisdom to find ways to devise solutions. In 2005, four victims of forced labor filed a damage suit against Japanese companies that mobilized Korean workers in the colonial period. In 2018, the Supreme Court of Korea ruled in their favor. Although the Supreme Court acknowledged the validity of the 1965 Claims Agreement between Korea and Japan, it ruled that the right of an individual to claim damages against unlawful acts had never been waived. A Supreme Court ruling has the highest legal authority and executory power within the Republic of Korea. My Administration respects the judiciary’s decision, and we have been engaging in consultations with the Japanese Government on how to reach a satisfactory resolution to which the victims could agree. The door for such consultations remains wide open. My Administration is ready to sit down with the Japanese Government at any time to discuss these issues. Three of the plaintiffs have already passed away. When Japan’s export restriction measures were put in place last year, Lee Chun-sik, now the sole surviving plaintiff, wondered out loud whether the Republic of Korea was “suffering a loss” because of him. We will affirm the fact that protecting an individual’s dignity will never end up incurring a loss for his country. At the same time, we will work with Japan to protect universal values of humanity, the principles of international law and democracy based on the separation of powers. I believe that joint efforts by Japan and Korea to respect individual human rights will become a bridge for friendship and future cooperation between the peoples of our two countries. Fellow Koreans, Dongdaemun Stadium is a place imbued with both the joy of liberation and the pain of inter-Korean division. On December 19, 1945, a national ceremony to welcome the Provisional Republic of Korea Government was held here. That day, independence activist Kim Gu – pen name Baekbeom – called on the public to “Let the entire Korean people unite and build a new Korea of self-reliance, equality and happiness.” However, on July 5, 1949, our people had to bid him a tearful farewell, as one million mourners gathered here. Kim Gu dreamed of completing the liberation of Korea that was left unfinished due to the division by bringing about the unification of the Korean Peninsula. That dream has become a task for all of us who remain. Genuine liberation can be achieved when the dreams and lives of each and every one of us are guaranteed on a unified, peaceful and safe Korean Peninsula. The reason we pursue peace and promote inter-Korean cooperation is to ensure that the people of the two Koreas can live together, safe and well. We have awakened to the fact that everyone’s health and safety are closely connected as we fight infectious diseases in livestock and the COVID-19 pandemic while enduring unprecedented downpours triggered by extreme weather. The fact that South and North Korea are one community when it comes to life and safety has been confirmed repeatedly. Security and peace in this era are about guaranteeing the life and safety of everyone living on the Korean Peninsula. I hope that cooperation on epidemic prevention and control and the joint management of transboundary rivers will help the people of the two Koreas sense tangible benefits from peace. It is my hope that along with communities for peace and economic prosperity, there will be a breakthrough for mutual benefit and peace to achieve a community for life. This should accompany closer cooperation on a new security situation in the COVID-19 era through collaboration on healthcare, medical services and forestry and joint research on agricultural technology and the development of new crop varieties. Along with humanitarian cooperation for the life and safety of the people, working together to allow them to meet whomever they want and visit wherever they want before they die is practical inter-Korean collaboration. Inter-Korean cooperation is indeed the best security policy that allows both Koreas to break away from reliance on nuclear or military strength. The stronger inter-Korean cooperation grows, the more solid the security of each Korea will be. This will in turn become a force that moves us toward prosperity in cooperation with the international community. As agreed upon in the Panmunjom Declaration, we will permanently remove the threat of war and build the foundation of genuine liberation that our forebears dreamed of. The two Koreas conducted a joint survey of and even held a groundbreaking ceremony for the reconnection of inter-Korean railways. It is the key driving force to expand future inter-Korean cooperation into the continent. We will move toward a Korean Peninsula of peace and common prosperity while examining and implementing every single aspect of agreements already reached between the two Koreas. Fellow Koreans, decorated independence activists, bereaved relatives and overseas Koreans, Here are our beliefs: sacrifice for our country will be remembered, our county will assure safety in the face of disasters and catastrophes, it will save us when we suffer hardships in a foreign land, it will attend to each individual’s difficulty and it will guarantee an opportunity to carry on even after a setback. These beliefs allow individuals to take on new challenges and endure hardships. When a country lives up to these beliefs, individuals – not just a nation – will be liberated. Dongdaemun Design Plaza is embedded with the sweat and smoldering frustration of a marathoner in the colonial era, the joy of liberation and lament over national division. Today, upon such historical strata, the creativity and individuality of each person is blossoming fully. Beyond the path to this democratic republic initiated a century ago, we will move with the people toward a Republic of Korea brimming with individual freedom and equality. Beyond the self-reliant independent country that our forebears envisioned, we will move toward a peaceful, prosperous and unified Korean Peninsula with the people. Thank you. LIST PRINT Remarks by President Moon Jae-in during Visit to Middle School Emerging as Green Smart School Message from President Moon Jae-in on National Day to Honor Japanese Military Comfort Women Victims PRESIDENT Greetings Profile Life Story The Administration SPEECHES & REMARKS BRIEFINGS Speeches & Remarks Briefings MEDIA Interviews Korea.net News CONTENTS Infographics Photos Videos Publications CONTACT General Information Tours CONTACT INFO *** 1 Cheongwadae-ro, Jongno-gu, Seoul 03048 Republic of Korea COPYRIGHT Office of the President. All rights reserved. | M12: Our liberation was obtained by each and every Korean rising together as the rightful owners of a democratic republic. All of those who have achieved accomplishments big and small as masters of their own lives comprise the roots of what we are today. Our forebears left us a conviction that has formed an immense root of our history: “If we unite, we can prevail over any crisis.” In the process of overcoming the COVID-19 outbreak, we have been able to reaffirm our capabilities while surmounting the crisis together. Presently, massive natural disasters caused by abnormal weather conditions are threatening our everyday lives yet again. Nonetheless, we will certainly prevail over them this time as we always have. We will confront disasters until they are over in order to protect the lives and property of the people. We will also do as much as we can for disaster recovery. Moreover, in preparation for extreme weather becoming increasingly severe, we will muster all available capabilities to safeguard the people’s safety, thereby sparing them from repeated suffering. I salute the decorated independence activists and bereaved families who have become a source of pride for the Republic of Korea. I promise that with the people we will weather today’s crisis and calamities without fail. Gyeongseong Stadium was built here during the Japanese colonial period and was renamed Seoul Stadium after liberation. Numerous sweat-stained historic chapters have been recorded on this site, which was long referred to as Dongdaemun Stadium. Among these, the beads of sweat shed by young Joseon marathoner Sohn Kee-chung under colonial rule must be remembered as the most ardent and regrettable. In 1935, he broke away from a field of runners in a 10,000 meter race at Gyeongseong Stadium and won. The next year, he set a world record while winning the marathon at the Berlin Olympics. As the Japanese national anthem began to play during the award ceremony, Olympic gold medalist Sohn Kee-chung hid the Japanese flag on his chest with the laurel sapling presented to him. The Korean Olympian Nam Seung-yong, who won bronze in that marathon, could only hang his head and close his eyes. They pulled off a great victory that helped restore Korean pride, but they had no country upon which to bestow that glory. From being the most impoverished country to receive international aid, we have soared to become one of the 10 largest global economic powerhouses. In the face of dictatorship, we left the world a milestone for democracy. Though we endured a period when individual sacrifices were demanded and human rights were oppressed in the name of the state, we have never stopped marching toward a properly functioning country where each citizen is guaranteed inherent rights for freedom, equality, dignity and safety. Our people have withstood many crises. We rose from the ashes of war and overcame the Asian foreign exchange and global financial crises. Together, we have also surmounted the crisis prompted by Japan’s export restrictions. We have actually turned that into an opportunity to leap forward as a nation that cannot be shaken. Mutually beneficial cooperation between large businesses and SMEs has led to independence in the production of materials, parts and equipment. Some of these ventures have even attracted foreign investors. Amid the global economic crisis, Korea’s economic growth this year is projected to rank first among the 37 OECD member states. Our GDP is also forecast to join the ranks of the 10 largest economies in the world. I cannot but extend my respect and gratitude to our people once again, who are turning crises into opportunities even while enduring great suffering. We have now affirmed the fact that our neighbors’ safety equals our own and are preparing for a post-COVID-19 era. While bringing implementation of the Korean New Deal into full gear, we will reform and upgrade our economic fundamentals – employing the Digital New Deal and the Green New Deal as our wings. From a fast follower-type economy to a pace-setting one and from a carbon-dependent economy to a low-carbon one, we will fundamentally transform the Republic of Korea and once again leap forward. The spirit that permeates the core of the Korean New Deal is also people-centered mutual benefit. A new social contract for mutual benefit, the Korean New Deal is also a pledge to achieve and share prosperity together by further strengthening the employment and social safety nets and increasing investments in people. What matters the most is to reduce gaps and inequality. Only when everyone is living well can we say that genuine liberation has been achieved. I believe that the people will join us on the path toward sustainable development for both their own benefit as well as that of future generations. Fellow Koreans, In the winter of 2016, squares and streets throughout the country were filled with the spirit of Article 1 of the Constitution: All state authority shall emanate from the people. Our people held aloft lit candles and once more etched onto the chapters of history the fact that the power to change the world always rests with them. That spirit became the foundation of our Administration. Today, on the occasion of the 75th anniversary of Liberation Day, I look back to see whether each individual really has achieved liberation. However, we will give people the firm belief that our society is heading in that direction and do all we can to build a solid foundation. We remember our compatriots who emigrated from the Empire of Korea to work in Hawaii and Mexico but could not return as they lost their homeland. We must never forget that tearful history. Although the motherland could not protect its people, they collected wages from labor and spoonfuls of rice to fund the Provisional Republic of Korea Government’s independence movement. As such, they became a root of the overseas independence movement. We must remember forever those who were never able to return to the arms of their families in a liberated homeland. It was deeply meaningful to mark the centennials of the March First Independence Movement and the establishment of the Provisional Republic of Korea Government last year by repatriating the remains of five decorated independence activists. We as a nation must also respond without fail to the efforts of individuals to prove their own dignity and pool our wisdom to find ways to devise solutions. In 2005, four victims of forced labor filed a damage suit against Japanese companies that mobilized Korean workers in the colonial period. In 2018, the Supreme Court of Korea ruled in their favor. Although the Supreme Court acknowledged the validity of the 1965 Claims Agreement between Korea and Japan, it ruled that the right of an individual to claim damages against unlawful acts had never been waived. A Supreme Court ruling has the highest legal authority and executory power within the Republic of Korea. My Administration respects the judiciary’s decision, and we have been engaging in consultations with the Japanese Government on how to reach a satisfactory resolution to which the victims could agree. The door for such consultations remains wide open. My Administration is ready to sit down with the Japanese Government at any time to discuss these issues. Three of the plaintiffs have already passed away. When Japan’s export restriction measures were put in place last year, Lee Chun-sik, now the sole surviving plaintiff, wondered out loud whether the Republic of Korea was “suffering a loss” because of him. We will affirm the fact that protecting an individual’s dignity will never end up incurring a loss for his country. At the same time, we will work with Japan to protect universal values of humanity, the principles of international law and democracy based on the separation of powers. Inter-Korean cooperation is indeed the best security policy that allows both Koreas to break away from reliance on nuclear or military strength. The stronger inter-Korean cooperation grows, the more solid the security of each Korea will be. This will in turn become a force that moves us toward prosperity in cooperation with the international community. As agreed upon in the Panmunjom Declaration, we will permanently remove the threat of war and build the foundation of genuine liberation that our forebears dreamed of. The two Koreas conducted a joint survey of and even held a groundbreaking ceremony for the reconnection of inter-Korean railways. It is the key driving force to expand future inter-Korean cooperation into the continent. We will move toward a Korean Peninsula of peace and common prosperity while examining and implementing every single aspect of agreements already reached between the two Koreas. Fellow Koreans, decorated independence activists, bereaved relatives and overseas Koreans, Here are our beliefs: sacrifice for our country will be remembered, our county will assure safety in the face of disasters and catastrophes, it will save us when we suffer hardships in a foreign land, it will attend to each individual’s difficulty and it will guarantee an opportunity to carry on even after a setback. These beliefs allow individuals to take on new challenges and endure hardships. Dongdaemun Design Plaza is embedded with the sweat and smoldering frustration of a marathoner in the colonial era, the joy of liberation and lament over national division. Today, upon such historical strata, the creativity and individuality of each person is blossoming fully. Beyond the path to this democratic republic initiated a century ago, we will move with the people toward a Republic of Korea brimming with individual freedom and equality. Beyond the self-reliant independent country that our forebears envisioned, we will move toward a peaceful, prosperous and unified Korean Peninsula with the people. Thank you. LIST PRINT Remarks by President Moon Jae-in during Visit to Middle School Emerging as Green Smart School Message from President Moon Jae-in on National Day to Honor Japanese Military Comfort Women Victims PRESIDENT Greetings Profile Life Story The Administration SPEECHES & REMARKS BRIEFINGS Speeches & Remarks Briefings MEDIA Interviews Korea.net News CONTENTS Infographics Photos Videos Publications CONTACT General Information Tours CONTACT INFO *** 1 Cheongwadae-ro, Jongno-gu, Seoul 03048 Republic of Korea COPYRIGHT Office of the President. All rights reserved. | N12: FORCED_LABOR | O12: COMPENSATION_REPARATION;COLONIAL_RULE | P12: 1 | Q12: 1 | R12: 1 | S12: HIGH | T12: 0 | U12: 1 | V12: 0 | W12: 0 | X12: 1 | Y12: 0 | Z12: OTHER | AA12: 1 | AB12: MIXED | AC12: en | AD12: 1 | AE12: http://webarchives.pa.go.kr/19th/english.president.go.kr/BriefingSpeeches/Speeches/861 | AF12: NA | AG12: NA | AH12: NA | AI12: 75th Liberation Day address. Substantial passage on the 2018 Korean Supreme Court ruling in favor of forced-labor victims against Japanese companies (names plaintiff Lee Chun-sik), Japan's 2019 export restrictions (widely read as retaliation), and Moon's offer to keep consultations with the Japanese government open. responsibility_actor=OTHER/agency_explicit=1: the passage explicitly names "Japanese companies that mobilized Korean workers in the colonial period" as the defendant/responsible party in the court case, though Moon himself does not editorialize further on blame. | AJ12: HIGH | AK12: ee60a891-51b2-58dd-a9b9-9c52d5ee464a | AL12: 1
A13: 659994d6-685f-4097-be80-e57c2fe585aa | B13: korea | C13: 2021-08-15 | D13: 2021 | E13: Moon Jae-in | F13: President of the Republic of Korea | G13: HEAD | H13: Office of the President, Republic of Korea (via National Archives of Korea web archive) | I13: PRESS_CONFERENCE | J13: Address by President Moon Jae-in on Korea’s 76th Liberation Day | L13: Address by President Moon Jae-in on Korea’s 76th Liberation Day 컨텐츠바로가기 Skip To main Contents ﻿ 이 웹사이트는 제19대 대통령 임기 종료에 따라 대통령기록관이 「대통령기록물 관리에 관한 법률」에 의해 이관받아 서비스하는 대통령기록물입니다. 자료의 열람만 가능하며 수정 · 추가 · 삭제는 불가능합니다. 다만, 「개인정보보호법」 에 의하여 개인의 정보를 보호받기 원하시는 분은 관련 내용(요청자, 요청내용, 연락처, 글위치)을 대통령 웹기록물 담당자(044-211-2253)에게 요청해 주시면 신속히 검토하여 조치해 드리겠습니다. 감사합니다. [오늘 그만 보기] 이 웹사이트는 국민의 알권리 보장을 위해 대통령기록관에서 보존·서비스하고 있는 대통령기록물입니다. This Website is the Presidential Records maintained and serviced by the Presidential Archives of Korea to ensure the people's right to know. PRESIDENT Greetings Profile Life Story The Administration SPEECHES & REMARKS BRIEFINGS Speeches & Remarks Briefings MEDIA Interviews Korea.net News CONTENTS Infographics Photos Videos Publications CONTACT General Information Tours Search KR JP CN Twitter SPEECHES & REMARKS BRIEFINGS SPEECHES & REMARKS BRIEFING Address by President Moon Jae-in on Korea’s 76th Liberation Day August 15, 2021 Share (Unofficial Translation) Fellow Koreans, decorated independence activists, relatives of those departed and all Koreans living abroad, Today, as we mark the 76th Liberation Day, the remains of General Hong Beom-do will finally arrive in his homeland. General Hong was the commander of the Greater Korea Independence Army that fought against imperial Japan from bases in China. He spearheaded historic victories at the battles of Fengwudong and Qingshanli. Later, he became a spiritual anchor for the ethnic Koreans that migrated to Kazakhstan. I am very pleased that my Administration’s diplomatic efforts to repatriate his remains have come to fruition. I am deeply grateful to Kazakh President Tokayev and the Korean diaspora there for all of their cooperation, both emotionally and materially. As of today, the remains of 144 patriotic independence activists have been returned to their home country, starting with those of the patriotic martyrs Yun Bong-gil and Lee Bong-chang in 1946 right after liberation on up to General Hong Beom-do’s today. It is indisputably our duty and privilege as a nation and descendants to bring our independence heroes back home. We will do our best to that end. Regardless of the hardships faced, our forebears never lost sight of their dream – self-reliant independence. They mounted a Korean independence movement wherever they found a home. Their indomitable will has been steadily carried on by posterity and, even now, serves as a source of strength to overcome national crises. I extend my deepest respect and gratitude to our forebears, decorated independence activists and their bereaved families. Fellow Koreans, Culture Station Seoul 284, where this ceremony is being held today, was a place of suffering and sorrow during the Japanese colonial period. Crops and goods produced on our land were plundered and shipped out from here. At this place, independence activists who set out on perilous paths and farmers who lost their fields bid farewell to their homeland. Student soldiers who were forcibly dragged off to battlefields in the prime of their youth and their loved ones shed tears here. However, this station and its square came to house dreams and hopes after the country was liberated. Trains that departed from Manchuria and Russia’s Maritime Province in Siberia were full of Koreans coming back to their hometowns. Busan, Incheon, Gunsan and other port cities were bustling with returnees filled with hope. The overwhelming emotions and hopes that were felt on Liberation Day are still a part of our future. The hearts of all our people swelled with the vision of building a new nation. Fathers and mothers dedicated their lives to securing an education for their children. There had been 1.45 million primary, middle and high school students across the country at that time, but just two years after liberation, the number increased more than 60 percent to 2.35 million. People’s ardent zeal for education drove the country to introduce compulsory education. Talented individuals became the growth engines of the Republic of Korea. Agricultural production also rose significantly. Crop yields, which had been suppressed due to pillage from imperial Japan, surged after farmland reforms. Around the 1970s, they showed a three-fold increase from the Japanese colonial period, finally making it possible to end our recurring periods of scarce food. The people’s determination to “be well off,” which sprang from the 1960s’ five-year Economic Development Plans, led to the Socioeconomic Development Plan and New Economic Plan and fostered the IT industry as well as green growth and the creative economy. It has served as the foundation for Korea to emerge as one of the world’s 10 largest economic powerhouses. The country’s per capita GDP surpassed US$30,000 in 2017 and also overtook that of a G7 member state last year. Self-reliant national defense has been our desperate dream for the past century. Upholding the spirit of the independence armies and the Korean Liberation Army, our Army has grown into a cutting-edge, formidable military force that has deployed the world-class K2 Black Panther tank, K9 Thunder self-propelled howitzer and K21 infantry fighting vehicle. Our Navy, founded with patrol boats and rusted battleships abandoned by the Japanese military, has become an oceangoing navy that has commissioned some 150 naval vessels in total, including 19 submarines and nine destroyers – some of which are armed with the Aegis Weapon System. Our Air Force had only 20 light aircraft back in 1949, but it has become only the eighth air force in the world to independently develop an advanced supersonic fighter jet – the KF-21 – and is soaring into space as a mighty air force. Now, Korea is the 6th strongest military powerhouse in the 2021 Global Firepower ranking. To prepare for the Fourth Industrial Revolution and new security environment in the space era, we are building defense capabilities that no one dare challenge. Korean independence movement leader Kim Gu, pen name Baekbeom, envisioned “a state with a highly developed culture.” Today, his aspiration is being fulfilled on the global stage through our culture and arts. BTS recently became the first band to replace itself at the top of the Billboard chart with a new single. The film “Parasite” won the top prize at Cannes and multiple Oscars at the Academy Awards. Actress Youn Yuh-jung won the Best Supporting Actress Oscar. Not only K-pop and our movies but also games, TV dramas, webtoons, animation and content in various other fields are loved around the world. Annual content exports broke the US$10 billion mark for the first time last year. The high caliber of our culture and arts are not limited to modern and popular genres. Our culture and arts figures have made remarkable achievements even in such traditional fields as classical music and ballet. Embracing traditional and modern elements harmoniously, they have achieved such feats through creativity and passion. These accomplishments represent the potential of the Korean people who love culture and the arts. Fellow Koreans, We have always had new dreams. We have been able to come this far as we have not lost those dreams. Our dreams for independence, liberty and decent lives set the country free. This past June, the United Nations Conference on Trade and Development unanimously agreed to upgrade the status of Korea to an advanced economy, the first time ever for a developing nation. As we have now become an advanced country, we have yet another dream: to become a peaceful, dignified advanced nation and to become a country that fulfills its fair share of duties within the international community. We have pioneered a path that had never been traveled. Emerging from colonial rule and third-world status, we have forged a new model of success for developing economies. Our most unique and greatest strength lies in the fact that we can share our growth experience with developing countries. In confronting the raging challenges posed by COVID-19, we have demonstrated the power of our people’s strong sense of community, giving the world an example of how to overcome crises. We have inherited from our ancestors the resilient power of mutual benefit and cooperation. Even after suffering humiliation, discrimination, violence and exploitation under colonial rule, our forebears opted to embrace rather than retaliate against the Japanese still in our newly liberated country. We have always come together with one mind to fulfill our dreams. We have banded together even more tightly in the face of a crisis. We have turned countless crises into opportunities while empowering one another. The power of working together for mutual benefit will enable us to move toward new dreams and take the lead in the post-COVID-19 era. The country that all of our people envisioned through the candlelight revolution was “a properly functioning country” and “a country where everyone prospers.” We are expanding basic labor rights by implementing the 52-hour workweek system, raising the minimum wage and ratifying key ILO conventions. By increasing the number of employment insurance subscribers, raising senior citizens’ basic pension, strengthening the coverage of health insurance and implementing a national system that cares for dementia patients, we are enhancing the inclusiveness of our society. When it comes to the COVID-19 crisis – compared to any other advanced nation – our country is overcoming it in a stable manner. We will also surely prevail over this fourth wave fueled by the spread of the Delta variant. The inoculation is also approaching its target. In October, 70 percent of the total population will have received their second shots, and vaccination rate targets will be raised once more. We will recover together and leap forward together. Extensive compensation will be provided to cover COVID-19-related damage to microbusiness owners, and everything possible will be done to create decent jobs and increase employment opportunities for the vulnerable. We will expand the living allowance support for low-income families to achieve an inclusive recovery that reduces disparities. The world order is taking shape anew. At this critical watershed in history, the Republic of Korea is facing an opportunity to move toward a pacesetting country. A pacesetting economy uses creative ideas as its core competitiveness, and its growth pivots around people. The number of unicorn companies increased to 15 last year, and venture investments in the first half of this year reached a record high. As such, the second venture boom is spreading. Having claimed the top spot in global shipbuilding orders and become one of the top five automobile manufacturers in the world, our country has built on its success with memory semiconductors and has also been performing well in the system semiconductors market as well as those for batteries and biohealth. Amid this process, exports are setting new records. The Government will make our economy stronger by instilling the values of innovation, mutual benefit and inclusiveness. The Korean New Deal, through which a total of 220 trillion won will be invested by 2025, is both a roadmap for moving toward a people-centered, innovative and inclusive country and a national development strategy to achieve a new leap forward. In addition to the Korean New Deal’s Digital and Green New Deals, the Government has erected yet another support pillar: the Human New Deal. We will knit the social safety net more tightly – for instance, by introducing universal employment insurance and completely abolishing mandatory family support requirements – and spearhead the digital and green transitions through investments in people. We will provide young people with decent jobs by fostering workforces for such forward-looking sectors as software engineering and artificial intelligence. Our efforts will also focus on ensuring a just transition, so the digital and green transitions leave no one behind. The vision of balanced national development pursued by my Administration will become a reality through the Regionally Balanced New Deal. We will further strengthen financial decentralization for local areas and reverse the trend toward concentration in the Seoul metropolitan area. This will be made possible by sharing models of successful pan-regional cooperation as with the megacity in southeastern Korea. The economy is showing a fast and strong recovery, but its warmth has yet to reach many areas. By sharing the benefits of the economic recovery with all of our people, we will ensure that the vision of a country where everyone prospers becomes a tangible reality. Becoming a dignified advanced country begins with a culture of respect and consideration. We should move forward, one step closer to a society of inclusiveness and tolerance, not discrimination and exclusion. When we show consideration for the socially disadvantaged as well as acknowledge and respect the differences in each other’s positions and thoughts, our society will be able to move closer to being a dignified and respected advanced country. Fellow Koreans, In the process of emerging as an advanced country, we have been practicing the spirit of mutual benefit and cooperation across borders. By embracing market opening and trading nation status, Korea has become one of the world’s seven largest exporters and contributed to the development of the global economy. Since the inauguration, my Administration has expanded the scope of cooperation by signing the Regional Comprehensive Economic Partnership (RCEP) and concluding FTAs with Indonesia, Cambodia and Israel. If the world does not work together, we cannot prevail over COVID-19 and surmount the climate crisis. The Republic of Korea will serve as a bridging nation that spearheads mutually beneficial cooperation between advanced and developing countries. The Republic of Korea has been invited to the G7 Summit for two years in a row, which signifies the start of a new world order. Building upon capabilities nurtured through openness and cooperation, we will actively contribute to overcoming the COVID-19 crisis as well as to establishing a peaceful order and the reconstruction of the global economy in the post-COVID-19 era. In particular, we will take the lead in creating value and order in the new era based on our experience with economic growth – having moved from a developing to an advanced country – and the soft power amassed through Hallyu and Korea’s response to COVID-19. First, our country will become a vaccine hub. We will use our biopharmaceutical production capacity – the second largest in the world – and the Korea-U.S. global vaccine partnership to take the lead in overcoming crises from infectious diseases that all of humanity faces. On the 5th of this month, a committee was launched to hasten our becoming a global vaccine hub. It will play a pivotal role by providing intensive support for developing and supplying the raw and processed materials needed for vaccines. The Government will join the efforts of businesses to put the first homegrown vaccine on the market before the end of the first half next year. Second, we will further enhance our role in the global supply chain. With semiconductors and batteries – industries where Korea has unmatched competitiveness – we can contribute to supply chain stability worldwide. We will solidify our position as a leading international base by making current technological gaps even wider. Third, we will fulfill our responsibilities as needed to tackle the climate crisis. Last year, we set out to achieve a new milestone by declaring “2050 Carbon Neutrality.” This goal was made possible thanks to people voluntarily working for the environment and businesses actively seeking management guided by ESG best practices. With the 2050 Carbon Neutrality plan announced on August 5, the Government will fulfill its responsibilities as a member of the international community by canvassing public opinion broadly and pledging feasible greenhouse gas reductions within this year through a 2030 Nationally Determined Contribution. Achieving 2050 carbon neutrality will by no means be easy, but it should not be perceived merely as a burden. This grand, global socioeconomic transformation toward carbon neutrality will bring unprecedented innovations and create numerous jobs. This is also a golden opportunity for us to leap forward as a pacesetting nation. The Government has nurtured eco-friendly vehicles, batteries and the hydrogen economy as future growth engines. We are expanding such new and renewable energy power generation as solar and offshore wind power while reducing coal’s role in our power mix. We will take the initiative in our transitioning to a low-carbon economy by focusing on the fields in which we currently lead. The scope of international solidarity and cooperation will also be expanded. In particular, we will assist energy transitions among developing countries that are highly dependent on coal to generate power and share green technologies and knowledge gained from our Green New Deal. Fellow Koreans, On August 16, 1945, the day after our liberation, Ahn Jae-hong – a nation leader – gave a speech broadcast to 30 million Koreans. Then vice chairman of the Preparatory Committee for National Construction, Ahn proposed that defeated Japan and liberated Korea move toward an equal and mutually beneficial relationship. It is truly a bold and inclusive sense of history that transcends the victim mentality of the colonized. National consciousness was heightened to the fullest after liberation, but we did not drift toward an exclusive or hostile form of nationalism. Pursuing world peace and happiness for all people, moving beyond Asia, is the spirit of the March First Independence Movement. This is the great founding spirit that the Provisional Republic of Korea Government and its liberated people practiced. The Republic of Korea has consistently upheld that spirit. Since normalizing diplomatic relations, Korea and Japan have long been able to achieve economic growth together through a division of labor and cooperation based on the common shared values of democracy and a market economy. This is the direction our two countries should continue to go in, moving forward together. Our Government has always kept the door open for dialogue to jointly respond not only to our two countries’ pending issues but also threats facing the world, including COVID-19 and the climate crisis. For historical issues that need to be rectified, we will resolve them through actions and practices that are consistent with universal values and the standards of the international community. I look forward to our two countries gathering wisdom and surmounting difficulties together, setting an example of the cooperation expected between neighbors. This year marks the 30th anniversary of South and North Korea’s joint accession to the United Nations. One year before that, in 1990, East and West Germany achieved unification after 45 years of division. East and West Germany built trust by exchanging good faith and intentions. They created a “German model” that pursues universalism, pluralism, coexistence and co-prosperity. Moreover, by overcoming neighboring countries’ concerns about their unification through sincere reflection on the past, Germany has become a pacesetting country in the European Union, a leader championing universal values and standards shared globally. Division is the biggest obstacle blocking our growth and prosperity and simultaneously a tenacious barrier to permanent peace. Like Germany, we can also remove this barrier. Although unification may take some more time, we can create a Korean Peninsula model in which the two Koreas coexist and contribute to the prosperity of Northeast Asia as a whole through denuclearization and permanent peace on the Peninsula. The Northeast Asia Cooperation Initiative for Infectious Disease Control and Public Health is now discussing sharing information and cooperating on projects such as the joint stockpiling of medical and epidemic prevention supplies and joint training of personnel to respond to COVID-19. Since COVID-19 is now clearly not a temporary threat, the importance of such cooperation has become all the more significant. While expanding cooperation, we will work hard to ensure that North Korea, a member of the East Asian community of life, can participate as well. Firmly institutionalizing peace on the Korean Peninsula will definitely benefit both Koreas greatly. Most of all, the advantages that the Republic of Korea would be able to enjoy will be enormous once we shake off the so-called Korea discount and connect to the continent rather than exist as a virtual island nation. If we tirelessly envision peace on the Korean Peninsula, our imaginations can reach beyond it and spread across Eurasia. If we do not stop striving for reconciliation and cooperation, that tenacious barrier will finally crumble and new hopes and prosperity beyond our dreams will begin. Fellow Koreans, decorated independence activities, relatives of those departed, and all Koreans living abroad, Despite colonization and the ruins of war, we have held onto our passion and dream for a better future. We have taken steps to become a country that has proudly advanced, a country that prospers with its neighbors and a country that prevails over division and pursues peace. Anyone who travels abroad would be able to sense that others have a much higher opinion of us than we have of ourselves. The international community is amazed at the Republic of Korea’s capabilities and achievements in many fields, including the economy, epidemic prevention and control, democracy, culture and the arts. We are not the Republic of Korea of the past. It is our turn to be proud of ourselves and dream once more. I hope that all of our people will move forward together toward that vision. I pay homage with all my heart to our forebears who have bequeathed a great legacy – a strong will for freedom and peace, a dedication to community and solidarity and cooperation. Thank you. LIST PRINT Remarks by President Moon Jae-in at Posthumous Presentation of Order of Merit to General Hong Beom-do Remarks by President Moon Jae-in on Achievements of Policy Expanding National Health Insurance Coverage upon Its Fourth Anniversary PRESIDENT Greetings Profile Life Story The Administration SPEECHES & REMARKS BRIEFINGS Speeches & Remarks Briefings MEDIA Interviews Korea.net News CONTENTS Infographics Photos Videos Publications CONTACT General Information Tours CONTACT INFO *** 1 Cheongwadae-ro, Jongno-gu, Seoul 03048 Republic of Korea COPYRIGHT Office of the President. All rights reserved. | M13: Their indomitable will has been steadily carried on by posterity and, even now, serves as a source of strength to overcome national crises. I extend my deepest respect and gratitude to our forebears, decorated independence activists and their bereaved families. Fellow Koreans, Culture Station Seoul 284, where this ceremony is being held today, was a place of suffering and sorrow during the Japanese colonial period. Crops and goods produced on our land were plundered and shipped out from here. At this place, independence activists who set out on perilous paths and farmers who lost their fields bid farewell to their homeland. Korean independence movement leader Kim Gu, pen name Baekbeom, envisioned “a state with a highly developed culture.” Today, his aspiration is being fulfilled on the global stage through our culture and arts. BTS recently became the first band to replace itself at the top of the Billboard chart with a new single. The film “Parasite” won the top prize at Cannes and multiple Oscars at the Academy Awards. Actress Youn Yuh-jung won the Best Supporting Actress Oscar. Not only K-pop and our movies but also games, TV dramas, webtoons, animation and content in various other fields are loved around the world. As we have now become an advanced country, we have yet another dream: to become a peaceful, dignified advanced nation and to become a country that fulfills its fair share of duties within the international community. We have pioneered a path that had never been traveled. Emerging from colonial rule and third-world status, we have forged a new model of success for developing economies. Our most unique and greatest strength lies in the fact that we can share our growth experience with developing countries. In confronting the raging challenges posed by COVID-19, we have demonstrated the power of our people’s strong sense of community, giving the world an example of how to overcome crises. We have inherited from our ancestors the resilient power of mutual benefit and cooperation. Even after suffering humiliation, discrimination, violence and exploitation under colonial rule, our forebears opted to embrace rather than retaliate against the Japanese still in our newly liberated country. We have always come together with one mind to fulfill our dreams. We have banded together even more tightly in the face of a crisis. We have turned countless crises into opportunities while empowering one another. The power of working together for mutual benefit will enable us to move toward new dreams and take the lead in the post-COVID-19 era. The country that all of our people envisioned through the candlelight revolution was “a properly functioning country” and “a country where everyone prospers.” We are expanding basic labor rights by implementing the 52-hour workweek system, raising the minimum wage and ratifying key ILO conventions. By increasing the number of employment insurance subscribers, raising senior citizens’ basic pension, strengthening the coverage of health insurance and implementing a national system that cares for dementia patients, we are enhancing the inclusiveness of our society. The inoculation is also approaching its target. In October, 70 percent of the total population will have received their second shots, and vaccination rate targets will be raised once more. We will recover together and leap forward together. Extensive compensation will be provided to cover COVID-19-related damage to microbusiness owners, and everything possible will be done to create decent jobs and increase employment opportunities for the vulnerable. We will expand the living allowance support for low-income families to achieve an inclusive recovery that reduces disparities. The world order is taking shape anew. At this critical watershed in history, the Republic of Korea is facing an opportunity to move toward a pacesetting country. A pacesetting economy uses creative ideas as its core competitiveness, and its growth pivots around people. The number of unicorn companies increased to 15 last year, and venture investments in the first half of this year reached a record high. Amid this process, exports are setting new records. The Government will make our economy stronger by instilling the values of innovation, mutual benefit and inclusiveness. The Korean New Deal, through which a total of 220 trillion won will be invested by 2025, is both a roadmap for moving toward a people-centered, innovative and inclusive country and a national development strategy to achieve a new leap forward. In addition to the Korean New Deal’s Digital and Green New Deals, the Government has erected yet another support pillar: the Human New Deal. We will knit the social safety net more tightly – for instance, by introducing universal employment insurance and completely abolishing mandatory family support requirements – and spearhead the digital and green transitions through investments in people. We will provide young people with decent jobs by fostering workforces for such forward-looking sectors as software engineering and artificial intelligence. Our efforts will also focus on ensuring a just transition, so the digital and green transitions leave no one behind. The vision of balanced national development pursued by my Administration will become a reality through the Regionally Balanced New Deal. We will further strengthen financial decentralization for local areas and reverse the trend toward concentration in the Seoul metropolitan area. This will be made possible by sharing models of successful pan-regional cooperation as with the megacity in southeastern Korea. The economy is showing a fast and strong recovery, but its warmth has yet to reach many areas. By sharing the benefits of the economic recovery with all of our people, we will ensure that the vision of a country where everyone prospers becomes a tangible reality. Becoming a dignified advanced country begins with a culture of respect and consideration. We should move forward, one step closer to a society of inclusiveness and tolerance, not discrimination and exclusion. When we show consideration for the socially disadvantaged as well as acknowledge and respect the differences in each other’s positions and thoughts, our society will be able to move closer to being a dignified and respected advanced country. Fellow Koreans, In the process of emerging as an advanced country, we have been practicing the spirit of mutual benefit and cooperation across borders. With the 2050 Carbon Neutrality plan announced on August 5, the Government will fulfill its responsibilities as a member of the international community by canvassing public opinion broadly and pledging feasible greenhouse gas reductions within this year through a 2030 Nationally Determined Contribution. Achieving 2050 carbon neutrality will by no means be easy, but it should not be perceived merely as a burden. This grand, global socioeconomic transformation toward carbon neutrality will bring unprecedented innovations and create numerous jobs. This is also a golden opportunity for us to leap forward as a pacesetting nation. The Government has nurtured eco-friendly vehicles, batteries and the hydrogen economy as future growth engines. We are expanding such new and renewable energy power generation as solar and offshore wind power while reducing coal’s role in our power mix. In particular, we will assist energy transitions among developing countries that are highly dependent on coal to generate power and share green technologies and knowledge gained from our Green New Deal. Fellow Koreans, On August 16, 1945, the day after our liberation, Ahn Jae-hong – a nation leader – gave a speech broadcast to 30 million Koreans. Then vice chairman of the Preparatory Committee for National Construction, Ahn proposed that defeated Japan and liberated Korea move toward an equal and mutually beneficial relationship. It is truly a bold and inclusive sense of history that transcends the victim mentality of the colonized. National consciousness was heightened to the fullest after liberation, but we did not drift toward an exclusive or hostile form of nationalism. Pursuing world peace and happiness for all people, moving beyond Asia, is the spirit of the March First Independence Movement. This is the great founding spirit that the Provisional Republic of Korea Government and its liberated people practiced. The Republic of Korea has consistently upheld that spirit. Since normalizing diplomatic relations, Korea and Japan have long been able to achieve economic growth together through a division of labor and cooperation based on the common shared values of democracy and a market economy. This is the direction our two countries should continue to go in, moving forward together. Our Government has always kept the door open for dialogue to jointly respond not only to our two countries’ pending issues but also threats facing the world, including COVID-19 and the climate crisis. For historical issues that need to be rectified, we will resolve them through actions and practices that are consistent with universal values and the standards of the international community. I look forward to our two countries gathering wisdom and surmounting difficulties together, setting an example of the cooperation expected between neighbors. This year marks the 30th anniversary of South and North Korea’s joint accession to the United Nations. One year before that, in 1990, East and West Germany achieved unification after 45 years of division. East and West Germany built trust by exchanging good faith and intentions. They created a “German model” that pursues universalism, pluralism, coexistence and co-prosperity. Moreover, by overcoming neighboring countries’ concerns about their unification through sincere reflection on the past, Germany has become a pacesetting country in the European Union, a leader championing universal values and standards shared globally. Division is the biggest obstacle blocking our growth and prosperity and simultaneously a tenacious barrier to permanent peace. Like Germany, we can also remove this barrier. If we tirelessly envision peace on the Korean Peninsula, our imaginations can reach beyond it and spread across Eurasia. If we do not stop striving for reconciliation and cooperation, that tenacious barrier will finally crumble and new hopes and prosperity beyond our dreams will begin. Fellow Koreans, decorated independence activities, relatives of those departed, and all Koreans living abroad, Despite colonization and the ruins of war, we have held onto our passion and dream for a better future. We have taken steps to become a country that has proudly advanced, a country that prospers with its neighbors and a country that prevails over division and pursues peace. Anyone who travels abroad would be able to sense that others have a much higher opinion of us than we have of ourselves. We are not the Republic of Korea of the past. It is our turn to be proud of ourselves and dream once more. I hope that all of our people will move forward together toward that vision. I pay homage with all my heart to our forebears who have bequeathed a great legacy – a strong will for freedom and peace, a dedication to community and solidarity and cooperation. Thank you. | N13: COLONIAL_RULE | O13: HISTORICAL_RECOGNITION_GENERAL | P13: 1 | Q13: 0 | R13: 1 | S13: HIGH | T13: 0 | U13: 1 | V13: 0 | W13: 1 | X13: 0 | Y13: 0 | Z13: OTHER | AA13: 1 | AB13: MIXED | AC13: en | AD13: 1 | AE13: http://webarchives.pa.go.kr/19th/english.president.go.kr/BriefingSpeeches/Speeches/1045 | AF13: NA | AG13: NA | AH13: NA | AI13: 76th Liberation Day address, held at Culture Station Seoul 284 (a site used to ship plundered Korean crops/goods under colonial rule). Describes forced conscription of "student soldiers," colonial-era exploitation ("pillage from imperial Japan"), but explicitly frames Korea's historical response as choosing to "embrace rather than retaliate against the Japanese," and calls for continuing the post-normalization cooperative economic relationship. reflection=1 for this explicit non-retaliation framing; no apology sought/given in this passage. | AJ13: HIGH | AK13: 4608f83f-39ee-5ca1-a4c8-b3248a8358d3 | AL13: 1
